Workbook

Sheet Инструкция
B1: ИНСТРУКЦИЯ И ОПИСАНИЕ ВЫПОЛНЕННЫХ ДЕЙСТВИЙ
B2: Книга-решение кейса «Интерактивная аналитика: создание дашбордов на Р7-Офис». Все преобразования выполнены формулами; исходные данные не изменялись (лежат на листах RAW_*).
B4: Структура книги
B5: Листы RAW_* | C5: Исходные данные «как есть» (Товары, Поставщики, Продажи, Клиенты). Все формулы очистки ссылаются на эти листы — оригинал остаётся неизменным.
B6: Листы *_очищенные | C6: Результат очистки. Серые столбцы — ссылки на исходные данные, жёлтые — промежуточные вычисления, зелёные — итоговые чистые значения, голубые — данные, подтянутые через ВПР/ИНДЕКС.
B7: Справочники | C7: Таблицы соответствий для ВПР: категории, статусы, валюты (курсы), сокращения городов.
B8: Итоговый_отчёт | C8: Статистика формулами (СЧЁТЗ, СЧЁТЕСЛИ, СУММЕСЛИМН) + 4 диаграммы.
B9: Макрос | C9: Код макроса Р7-Офис (Automation API) для автоматического пересчёта и выделения ошибок цветом.
B11: Этап 1. Товары_очищенные
B12: Стандартизация артикулов | C12: ПОДСТАВИТЬ — снятие префиксов «№АРТ-» и «АРТ_»; ЛЕВСИМВ(...;3) — первые 3 цифры = номер; сцепка "АРТ-"&номер → формат АРТ-XXX.
B13: Очистка наименований | C13: СЖПРОБЕЛЫ + ЛЕВСИМВ/НАЙТИ — удаление части в скобках; ПРОПНАЧ — каждое слово с заглавной буквы.
B14: Нормализация категорий | C14: ВПР по листу Справочники: Смартфоны/Телефоны/Мобильные телефоны → Смартфоны; Ноутбуки/Лэптопы → Ноутбуки.
B15: Приведение цен | C15: ПОДСТАВИТЬ — удаление пробелов-разделителей и замена запятой на точку; ЗНАЧЕН — в число; ОКРУГЛ(...;2) — два знака.
B16: Единицы измерения | C16: Любой вариант (шт/штука/штуки/шт.) приведён к «шт».
B17: Валидация | C17: ЕСЛИ — розница ≥ закупки; СЧЁТЕСЛИ — проверка уникальности артикула.
B19: Этап 2. Поставщики_очищенные
B20: Очистка ИНН | C20: ПОДСТАВИТЬ — удаление пробелов; ДЛСТР — проверка длины (10 или 12); ЕСЛИ — пометка «Ошибка ИНН».
B21: Телефоны | C21: Вложенные ПОДСТАВИТЬ — оставляем только цифры; ПСТР/ПРАВСИМВ — последние 10 цифр → формат +7 (XXX) XXX-XX-XX.
B22: Email | C22: СЖПРОБЕЛЫ/ПОДСТАВИТЬ — удаление пробелов; НАЙТИ — проверка «@» и точки в домене; иначе «Ошибка Email».
B23: Адреса | C23: ЛЕВСИМВ(...;6) — индекс в отдельный столбец; ПСТР — остаток адреса.
B25: Этап 3. Продажи_очищенные
B26: Конвертация дат | C26: ДАТА + ПСТР/ЛЕВСИМВ — из ММ/ДД/ГГГГ (США) в дату (формат ячейки ДД.ММ.ГГГГ).
B27: Количество | C27: ЗНАЧЕН(ЛЕВСИМВ(...)) — число до пробела; отрицательные значения (возвраты) сохранены.
B28: Конвертация валют | C28: Определение символа ($/€/₽) → ВПР по курсам (1$=95₽, 1€=100₽) → столбец Цена_продажи_руб.
B29: Нормализация статусов | C29: ВПР по справочнику статусов → Завершен / Отменен / Возврат.
B30: Удаление дубликатов | C30: Ключ Дата+Артикул+Клиент; СЧЁТЕСЛИ по нарастающему диапазону помечает повторы «ДУБЛЬ» (аналог инструмента «Удалить дубликаты»).
B31: Связывание данных | C31: ИНДЕКС/ПОИСКПОЗ (аналог ВПР) — подстановка розничной цены и категории из каталога по чистому артикулу.
B33: Этап 4. Клиенты_очищенные
B34: Нормализация ФИО | C34: СЖПРОБЕЛЫ + ПРОПНАЧ → «Фамилия Имя Отчество». Столбец-флаг отмечает записи с инициалами/латиницей для расшифровки/транслитерации.
B35: Очистка дат | C35: Распознавание двух форматов (ДД.ММ.ГГГГ и ГГГГ-ММ-ДД) через ЕСЛИ+НАЙТИ, приведение к дате.
B36: Валидация возраста | C36: ДАТАРАЗН(дата_рожд; СЕГОДНЯ(); "Y"); ЕСЛИ — возраст <18 или >120 → «Ошибка даты рождения».
B37: Телефоны и Email | C37: Те же правила, что для поставщиков.
B38: Города | C38: СЖПРОБЕЛЫ + ПОДСТАВИТЬ — снятие «г.»; ВПР по справочнику сокращений (МСК→Москва, СПб→Санкт-Петербург).
B40: Этап 5. Итоговая консолидация
B41: Единая книга | C41: Отдельные листы для каждого очищенного файла + справочники + отчёт.
B42: Статистика | C42: СЧЁТЗ — строки до/после; СЧЁТЕСЛИ — ошибки по типам и дубликаты; СУММЕСЛИМН — выручка по категориям.
B43: Диаграммы | C43: 4 диаграммы: строки до/после, ошибки по типам, распределение статусов (круговая), выручка по категориям.
B45: Использованные функции
B46: Текстовые | C46: СЖПРОБЕЛЫ (TRIM), ПСТР (MID), ЛЕВСИМВ (LEFT), ПРАВСИМВ (RIGHT), НАЙТИ (FIND), ПОДСТАВИТЬ (SUBSTITUTE), ПРОПНАЧ (PROPER), ДЛСТР (LEN), ЗНАЧЕН (VALUE), СЦЕПИТЬ (&).
B47: Поиск/ссылки | C47: ВПР (VLOOKUP), ИНДЕКС (INDEX), ПОИСКПОЗ (MATCH).
B48: Логика/проверка | C48: ЕСЛИ (IF), ЕСЛИОШИБКА (IFERROR), И (AND), ИЛИ (OR), ЕЧИСЛО (ISNUMBER), СЧЁТЕСЛИ (COUNTIF), СЧЁТЗ (COUNTA), СУММЕСЛИМН (SUMIFS).
B49: Дата | C49: ДАТА (DATE), ДАТАРАЗН (DATEDIF), СЕГОДНЯ (TODAY), ТЕКСТ (TEXT).

Sheet Товары_очищенные
A1: ЭТАП 1 — Очистка каталога товаров
A2: № | B2: Артикул (ориг.) | C2: Наименование (ориг.) | D2: Категория (ориг.) | E2: Производитель (ориг.) | F2: Цена_закупки (ориг.) | G2: Цена_розница (ориг.) | H2: Ед_изм (ориг.) | I2: Артикул_без_префикса | J2: Наимен_без_скобок | K2: Категория_для_ВПР | L2: Артикул_чист | M2: Наименование_чист | N2: Категория_чист | O2: Производитель_чист | P2: Цена_закупки_чист | Q2: Цена_розница_чист | R2: Ед_изм_чист | S2: Проверка_цен | T2: Уникальность_артикула
A3: 1 | B3: =RAW_Товары!A2 -> №АРТ-001/24 | C3: =RAW_Товары!B2 -> Смартфон Apple iPhone 15 | D3: =RAW_Товары!C2 -> Смартфоны | E3: =RAW_Товары!D2 -> Apple | F3: =RAW_Товары!E2 -> 45 000,50 | G3: =RAW_Товары!F2 -> 79 990,00 | H3: =RAW_Товары!G2 -> шт | I3: =SUBSTITUTE(SUBSTITUTE(B3,"№АРТ-",""),"АРТ_","") -> 001/24 | J3: =TRIM(LEFT(C3,IFERROR(FIND("(",C3)-1,LEN(C3)))) -> Смартфон Apple iPhone 15 | K3: =TRIM(D3) -> Смартфоны | L3: ="АРТ-"&LEFT(I3,3) -> АРТ-001 | M3: =PROPER(TRIM(J3)) -> Смартфон Apple Iphone 15 | N3: =IFERROR(VLOOKUP(K3,Справочники!$A$6:$B$16,2,0),"НЕТ В СПРАВОЧНИКЕ") -> Смартфоны | O3: =PROPER(TRIM(E3)) -> Apple | P3: =ROUND(VALUE(SUBSTITUTE(SUBSTITUTE(F3," ",""),",",".")),2) -> 45000.5 | Q3: =ROUND(VALUE(SUBSTITUTE(SUBSTITUTE(G3," ",""),",",".")),2) -> 79990 | R3: ="шт" -> шт | S3: =IF(Q3>=P3,"OK","ОШИБКА: розница < закупки") -> OK | T3: =IF(COUNTIF($L$3:$L$503,L3)=1,"уникален","ДУБЛЬ") -> уникален
A4: 2 | B4: =RAW_Товары!A3 -> АРТ_002 | C4: =RAW_Товары!B3 -> смартфон APPLE IPHONE 15 | D4: =RAW_Товары!C3 -> Телефоны | E4: =RAW_Товары!D3 -> Apple | F4: =RAW_Товары!E3 -> 44 500,00 | G4: =RAW_Товары!F3 -> 78 500,00 | H4: =RAW_Товары!G3 -> штука | I4: =SUBSTITUTE(SUBSTITUTE(B4,"№АРТ-",""),"АРТ_","") -> 002 | J4: =TRIM(LEFT(C4,IFERROR(FIND("(",C4)-1,LEN(C4)))) -> смартфон APPLE IPHONE 15 | K4: =TRIM(D4) -> Телефоны | L4: ="АРТ-"&LEFT(I4,3) -> АРТ-002 | M4: =PROPER(TRIM(J4)) -> Смартфон Apple Iphone 15 | N4: =IFERROR(VLOOKUP(K4,Справочники!$A$6:$B$16,2,0),"НЕТ В СПРАВОЧНИКЕ") -> Смартфоны | O4: =PROPER(TRIM(E4)) -> Apple | P4: =ROUND(VALUE(SUBSTITUTE(SUBSTITUTE(F4," ",""),",",".")),2) -> 44500 | Q4: =ROUND(VALUE(SUBSTITUTE(SUBSTITUTE(G4," ",""),",",".")),2) -> 78500 | R4: ="шт" -> шт | S4: =IF(Q4>=P4,"OK","ОШИБКА: розница < закупки") -> OK | T4: =IF(COUNTIF($L$3:$L$503,L4)=1,"уникален","ДУБЛЬ") -> уникален
A5: 3 | B5: =RAW_Товары!A4 -> 003/24 | C5: =RAW_Товары!B4 -> Смартфон Apple iPhone 15 (Черный) | D5: =RAW_Товары!C4 -> Мобильные телефоны | E5: =RAW_Товары!D4 -> APPLE | F5: =RAW_Товары!E4 -> 43 800,00 | G5: =RAW_Товары!F4 -> 77 700 | H5: =RAW_Товары!G4 -> штуки | I5: =SUBSTITUTE(SUBSTITUTE(B5,"№АРТ-",""),"АРТ_","") -> 003/24 | J5: =TRIM(LEFT(C5,IFERROR(FIND("(",C5)-1,LEN(C5)))) -> Смартфон Apple iPhone 15 | K5: =TRIM(D5) -> Мобильные телефоны | L5: ="АРТ-"&LEFT(I5,3) -> АРТ-003 | M5: =PROPER(TRIM(J5)) -> Смартфон Apple Iphone 15 | N5: =IFERROR(VLOOKUP(K5,Справочники!$A$6:$B$16,2,0),"НЕТ В СПРАВОЧНИКЕ") -> Смартфоны | O5: =PROPER(TRIM(E5)) -> Apple | P5: =ROUND(VALUE(SUBSTITUTE(SUBSTITUTE(F5," ",""),",",".")),2) -> 43800 | Q5: =ROUND(VALUE(SUBSTITUTE(SUBSTITUTE(G5," ",""),",",".")),2) -> 77700 | R5: ="шт" -> шт | S5: =IF(Q5>=P5,"OK","ОШИБКА: розница < закупки") -> OK | T5: =IF(COUNTIF($L$3:$L$503,L5)=1,"уникален","ДУБЛЬ") -> уникален
A6: 4 | B6: =RAW_Товары!A5 -> №АРТ-004 | C6: =RAW_Товары!B5 -> Ноутбук ASUS ROG Zephyrus | D6: =RAW_Товары!C5 -> Ноутбуки | E6: =RAW_Товары!D5 -> ASUS | F6: =RAW_Товары!E5 -> 85 000 | G6: =RAW_Товары!F5 -> 129 999.99 | H6: =RAW_Товары!G5 -> шт. | I6: =SUBSTITUTE(SUBSTITUTE(B6,"№АРТ-",""),"АРТ_","") -> 004 | J6: =TRIM(LEFT(C6,IFERROR(FIND("(",C6)-1,LEN(C6)))) -> Ноутбук ASUS ROG Zephyrus | K6: =TRIM(D6) -> Ноутбуки | L6: ="АРТ-"&LEFT(I6,3) -> АРТ-004 | M6: =PROPER(TRIM(J6)) -> Ноутбук Asus Rog Zephyrus | N6: =IFERROR(VLOOKUP(K6,Справочники!$A$6:$B$16,2,0),"НЕТ В СПРАВОЧНИКЕ") -> Ноутбуки | O6: =PROPER(TRIM(E6)) -> Asus | P6: =ROUND(VALUE(SUBSTITUTE(SUBSTITUTE(F6," ",""),",",".")),2) -> 85000 | Q6: =ROUND(VALUE(SUBSTITUTE(SUBSTITUTE(G6," ",""),",",".")),2) -> 129999.99 | R6: ="шт" -> шт | S6: =IF(Q6>=P6,"OK","ОШИБКА: розница < закупки") -> OK | T6: =IF(COUNTIF($L$3:$L$503,L6)=1,"уникален","ДУБЛЬ") -> уникален
A7: 5 | B7: =RAW_Товары!A6 -> АРТ_005 | C7: =RAW_Товары!B6 -> ноутбук ASUS ROG Zephyrus | D7: =RAW_Товары!C6 -> Лэптопы | E7: =RAW_Товары!D6 -> asus | F7: =RAW_Товары!E6 -> 84 500,50 | G7: =RAW_Товары!F6 -> 128 500,00 | H7: =RAW_Товары!G6 -> шт | I7: =SUBSTITUTE(SUBSTITUTE(B7,"№АРТ-",""),"АРТ_","") -> 005 | J7: =TRIM(LEFT(C7,IFERROR(FIND("(",C7)-1,LEN(C7)))) -> ноутбук ASUS ROG Zephyrus | K7: =TRIM(D7) -> Лэптопы | L7: ="АРТ-"&LEFT(I7,3) -> АРТ-005 | M7: =PROPER(TRIM(J7)) -> Ноутбук Asus Rog Zephyrus | N7: =IFERROR(VLOOKUP(K7,Справочники!$A$6:$B$16,2,0),"НЕТ В СПРАВОЧНИКЕ") -> Ноутбуки | O7: =PROPER(TRIM(E7)) -> Asus | P7: =ROUND(VALUE(SUBSTITUTE(SUBSTITUTE(F7," ",""),",",".")),2) -> 84500.5 | Q7: =ROUND(VALUE(SUBSTITUTE(SUBSTITUTE(G7," ",""),",",".")),2) -> 128500 | R7: ="шт" -> шт | S7: =IF(Q7>=P7,"OK","ОШИБКА: розница < закупки") -> OK | T7: =IF(COUNTIF($L$3:$L$503,L7)=1,"уникален","ДУБЛЬ") -> уникален
A8: 6 | B8: =RAW_Товары!A7 -> 006-24 | C8: =RAW_Товары!B7 -> Ноутбук ASUS ROG Zephyrus (G14) | D8: =RAW_Товары!C7 -> Ноутбуки | E8: =RAW_Товары!D7 -> ASUS | F8: =RAW_Товары!E7 -> 86 000 | G8: =RAW_Товары!F7 -> 131 000 | H8: =RAW_Товары!G7 -> штука | I8: =SUBSTITUTE(SUBSTITUTE(B8,"№АРТ-",""),"АРТ_","") -> 006-24 | J8: =TRIM(LEFT(C8,IFERROR(FIND("(",C8)-1,LEN(C8)))) -> Ноутбук ASUS ROG Zephyrus | K8: =TRIM(D8) -> Ноутбуки | L8: ="АРТ-"&LEFT(I8,3) -> АРТ-006 | M8: =PROPER(TRIM(J8)) -> Ноутбук Asus Rog Zephyrus | N8: =IFERROR(VLOOKUP(K8,Справочники!$A$6:$B$16,2,0),"НЕТ В СПРАВОЧНИКЕ") -> Ноутбуки | O8: =PROPER(TRIM(E8)) -> Asus | P8: =ROUND(VALUE(SUBSTITUTE(SUBSTITUTE(F8," ",""),",",".")),2) -> 86000 | Q8: =ROUND(VALUE(SUBSTITUTE(SUBSTITUTE(G8," ",""),",",".")),2) -> 131000 | R8: ="шт" -> шт | S8: =IF(Q8>=P8,"OK","ОШИБКА: розница < закупки") -> OK | T8: =IF(COUNTIF($L$3:$L$503,L8)=1,"уникален","ДУБЛЬ") -> уникален
A9: 7 | B9: =RAW_Товары!A8 -> №АРТ-007 | C9: =RAW_Товары!B8 -> Смартфон Samsung Galaxy S24 | D9: =RAW_Товары!C8 -> Смартфоны | E9: =RAW_Товары!D8 -> Samsung | F9: =RAW_Товары!E8 -> 39 999,99 | G9: =RAW_Товары!F8 -> 69 999,00 | H9: =RAW_Товары!G8 -> шт. | I9: =SUBSTITUTE(SUBSTITUTE(B9,"№АРТ-",""),"АРТ_","") -> 007 | J9: =TRIM(LEFT(C9,IFERROR(FIND("(",C9)-1,LEN(C9)))) -> Смартфон Samsung Galaxy S24 | K9: =TRIM(D9) -> Смартфоны | L9: ="АРТ-"&LEFT(I9,3) -> АРТ-007 | M9: =PROPER(TRIM(J9)) -> Смартфон Samsung Galaxy S24 | N9: =IFERROR(VLOOKUP(K9,Справочники!$A$6:$B$16,2,0),"НЕТ В СПРАВОЧНИКЕ") -> Смартфоны | O9: =PROPER(TRIM(E9)) -> Samsung | P9: =ROUND(VALUE(SUBSTITUTE(SUBSTITUTE(F9," ",""),",",".")),2) -> 39999.99 | Q9: =ROUND(VALUE(SUBSTITUTE(SUBSTITUTE(G9," ",""),",",".")),2) -> 69999 | R9: ="шт" -> шт | S9: =IF(Q9>=P9,"OK","ОШИБКА: розница < закупки") -> OK | T9: =IF(COUNTIF($L$3:$L$503,L9)=1,"уникален","ДУБЛЬ") -> уникален
A10: 8 | B10: =RAW_Товары!A9 -> АРТ_008 | C10: =RAW_Товары!B9 -> смартфон SAMSUNG GALAXY S24 | D10: =RAW_Товары!C9 -> Телефоны | E10: =RAW_Товары!D9 -> SAMSUNG | F10: =RAW_Товары!E9 -> 39 500 | G10: =RAW_Товары!F9 -> 68 900 | H10: =RAW_Товары!G9 -> штуки | I10: =SUBSTITUTE(SUBSTITUTE(B10,"№АРТ-",""),"АРТ_","") -> 008 | J10: =TRIM(LEFT(C10,IFERROR(FIND("(",C10)-1,LEN(C10)))) -> смартфон SAMSUNG GALAXY S24 | K10: =TRIM(D10) -> Телефоны | L10: ="АРТ-"&LEFT(I10,3) -> АРТ-008 | M10: =PROPER(TRIM(J10)) -> Смартфон Samsung Galaxy S24 | N10: =IFERROR(VLOOKUP(K10,Справочники!$A$6:$B$16,2,0),"НЕТ В СПРАВОЧНИКЕ") -> Смартфоны | O10: =PROPER(TRIM(E10)) -> Samsung | P10: =ROUND(VALUE(SUBSTITUTE(SUBSTITUTE(F10," ",""),",",".")),2) -> 39500 | Q10: =ROUND(VALUE(SUBSTITUTE(SUBSTITUTE(G10," ",""),",",".")),2) -> 68900 | R10: ="шт" -> шт | S10: =IF(Q10>=P10,"OK","ОШИБКА: розница < закупки") -> OK | T10: =IF(COUNTIF($L$3:$L$503,L10)=1,"уникален","ДУБЛЬ") -> уникален
A11: 9 | B11: =RAW_Товары!A10 -> 009/24 | C11: =RAW_Товары!B10 -> Смартфон Samsung Galaxy S24 (Синий) | D11: =RAW_Товары!C10 -> Мобильные телефоны | E11: =RAW_Товары!D10 -> Samsung | F11: =RAW_Товары!E10 -> 40 200 | G11: =RAW_Товары!F10 -> 70 500 | H11: =RAW_Товары!G10 -> шт | I11: =SUBSTITUTE(SUBSTITUTE(B11,"№АРТ-",""),"АРТ_","") -> 009/24 | J11: =TRIM(LEFT(C11,IFERROR(FIND("(",C11)-1,LEN(C11)))) -> Смартфон Samsung Galaxy S24 | K11: =TRIM(D11) -> Мобильные телефоны | L11: ="АРТ-"&LEFT(I11,3) -> АРТ-009 | M11: =PROPER(TRIM(J11)) -> Смартфон Samsung Galaxy S24 | N11: =IFERROR(VLOOKUP(K11,Справочники!$A$6:$B$16,2,0),"НЕТ В СПРАВОЧНИКЕ") -> Смартфоны | O11: =PROPER(TRIM(E11)) -> Samsung | P11: =ROUND(VALUE(SUBSTITUTE(SUBSTITUTE(F11," ",""),",",".")),2) -> 40200 | Q11: =ROUND(VALUE(SUBSTITUTE(SUBSTITUTE(G11," ",""),",",".")),2) -> 70500 | R11: ="шт" -> шт | S11: =IF(Q11>=P11,"OK","ОШИБКА: розница < закупки") -> OK | T11: =IF(COUNTIF($L$3:$L$503,L11)=1,"уникален","ДУБЛЬ") -> уникален
A12: 10 | B12: =RAW_Товары!A11 -> №АРТ-010 | C12: =RAW_Товары!B11 -> Планшет iPad Pro 12.9 | D12: =RAW_Товары!C11 -> Планшеты | E12: =RAW_Товары!D11 -> Apple | F12: =RAW_Товары!E11 -> 55 000 | G12: =RAW_Товары!F11 -> 89 900 | H12: =RAW_Товары!G11 -> шт. | I12: =SUBSTITUTE(SUBSTITUTE(B12,"№АРТ-",""),"АРТ_","") -> 010 | J12: =TRIM(LEFT(C12,IFERROR(FIND("(",C12)-1,LEN(C12)))) -> Планшет iPad Pro 12.9 | K12: =TRIM(D12) -> Планшеты | L12: ="АРТ-"&LEFT(I12,3) -> АРТ-010 | M12: =PROPER(TRIM(J12)) -> Планшет Ipad Pro 12.9 | N12: =IFERROR(VLOOKUP(K12,Справочники!$A$6:$B$16,2,0),"НЕТ В СПРАВОЧНИКЕ") -> Планшеты | O12: =PROPER(TRIM(E12)) -> Apple | P12: =ROUND(VALUE(SUBSTITUTE(SUBSTITUTE(F12," ",""),",",".")),2) -> 55000 | Q12: =ROUND(VALUE(SUBSTITUTE(SUBSTITUTE(G12," ",""),",",".")),2) -> 89900 | R12: ="шт" -> шт | S12: =IF(Q12>=P12,"OK","ОШИБКА: розница < закупки") -> OK | T12: =IF(COUNTIF($L$3:$L$503,L12)=1,"уникален","ДУБЛЬ") -> уникален
A13: 11 | B13: =RAW_Товары!A12 -> АРТ_011 | C13: =RAW_Товары!B12 -> планшет APPLE IPAD PRO 12.9 | D13: =RAW_Товары!C12 -> Планшеты | E13: =RAW_Товары!D12 -> apple | F13: =RAW_Товары!E12 -> 54 500 | G13: =RAW_Товары!F12 -> 88 500 | H13: =RAW_Товары!G12 -> штука | I13: =SUBSTITUTE(SUBSTITUTE(B13,"№АРТ-",""),"АРТ_","") -> 011 | J13: =TRIM(LEFT(C13,IFERROR(FIND("(",C13)-1,LEN(C13)))) -> планшет APPLE IPAD PRO 12.9 | K13: =TRIM(D13) -> Планшеты | L13: ="АРТ-"&LEFT(I13,3) -> АРТ-011 | M13: =PROPER(TRIM(J13)) -> Планшет Apple Ipad Pro 12.9 | N13: =IFERROR(VLOOKUP(K13,Справочники!$A$6:$B$16,2,0),"НЕТ В СПРАВОЧНИКЕ") -> Планшеты | O13: =PROPER(TRIM(E13)) -> Apple | P13: =ROUND(VALUE(SUBSTITUTE(SUBSTITUTE(F13," ",""),",",".")),2) -> 54500 | Q13: =ROUND(VALUE(SUBSTITUTE(SUBSTITUTE(G13," ",""),",",".")),2) -> 88500 | R13: ="шт" -> шт | S13: =IF(Q13>=P13,"OK","ОШИБКА: розница < закупки") -> OK | T13: =IF(COUNTIF($L$3:$L$503,L13)=1,"уникален","ДУБЛЬ") -> уникален
A14: 12 | B14: =RAW_Товары!A13 -> 012-24 | C14: =RAW_Товары!B13 -> Планшет Apple iPad Pro 12.9 (Wi-Fi) | D14: =RAW_Товары!C13 -> Планшеты | E14: =RAW_Товары!D13 -> Apple | F14: =RAW_Товары!E13 -> 56 000 | G14: =RAW_Товары!F13 -> 91 000 | H14: =RAW_Товары!G13 -> шт | I14: =SUBSTITUTE(SUBSTITUTE(B14,"№АРТ-",""),"АРТ_","") -> 012-24 | J14: =TRIM(LEFT(C14,IFERROR(FIND("(",C14)-1,LEN(C14)))) -> Планшет Apple iPad Pro 12.9 | K14: =TRIM(D14) -> Планшеты | L14: ="АРТ-"&LEFT(I14,3) -> АРТ-012 | M14: =PROPER(TRIM(J14)) -> Планшет Apple Ipad Pro 12.9 | N14: =IFERROR(VLOOKUP(K14,Справочники!$A$6:$B$16,2,0),"НЕТ В СПРАВОЧНИКЕ") -> Планшеты | O14: =PROPER(TRIM(E14)) -> Apple | P14: =ROUND(VALUE(SUBSTITUTE(SUBSTITUTE(F14," ",""),",",".")),2) -> 56000 | Q14: =ROUND(VALUE(SUBSTITUTE(SUBSTITUTE(G14," ",""),",",".")),2) -> 91000 | R14: ="шт" -> шт | S14: =IF(Q14>=P14,"OK","ОШИБКА: розница < закупки") -> OK | T14: =IF(COUNTIF($L$3:$L$503,L14)=1,"уникален","ДУБЛЬ") -> уникален
... A503: 501 | B503: =RAW_Товары!A502 -> 501/24 | C503: =RAW_Товары!B502 -> Клавиатура Logitech POP Keys (Pink) | D503: =RAW_Товары!C502 -> Аксессуары | E503: =RAW_Товары!D502 -> LOGITECH | F503: =RAW_Товары!E502 -> 4 000 | G503: =RAW_Товары!F502 -> 6 800 | H503: =RAW_Товары!G502 -> шт | I503: =SUBSTITUTE(SUBSTITUTE(B503,"№АРТ-",""),"АРТ_","") -> 501/24 | J503: =TRIM(LEFT(C503,IFERROR(FIND("(",C503)-1,LEN(C503)))) -> Клавиатура Logitech POP Keys | K503: =TRIM(D503) -> Аксессуары | L503: ="АРТ-"&LEFT(I503,3) -> АРТ-501 | M503: =PROPER(TRIM(J503)) -> Клавиатура Logitech Pop Keys | N503: =IFERROR(VLOOKUP(K503,Справочники!$A$6:$B$16,2,0),"НЕТ В СПРАВОЧНИКЕ") -> Аксессуары | O503: =PROPER(TRIM(E503)) -> Logitech | P503: =ROUND(VALUE(SUBSTITUTE(SUBSTITUTE(F503," ",""),",",".")),2) -> 4000 | Q503: =ROUND(VALUE(SUBSTITUTE(SUBSTITUTE(G503," ",""),",",".")),2) -> 6800 | R503: ="шт" -> шт | S503: =IF(Q503>=P503,"OK","ОШИБКА: розница < закупки") -> OK | T503: =IF(COUNTIF($L$3:$L$503,L503)=1,"уникален","ДУБЛЬ") -> уникален
B505: Легенда:
B506: Серые столбцы — исходные данные (ссылка на RAW_Товары).
B507: Жёлтые — промежуточные вычисления.
B508: Зелёные — итоговые очищенные значения.

Sheet Поставщики_очищенные
A1: ЭТАП 2 — Очистка справочника поставщиков
A2: № | B2: ID (ориг.) | C2: Название (ориг.) | D2: ИНН (ориг.) | E2: КПП (ориг.) | F2: Телефон (ориг.) | G2: Email (ориг.) | H2: Адрес (ориг.) | I2: ИНН_цифры | J2: Тел_цифры | K2: Email_без_пробелов | L2: Адрес_без_индекса | M2: ID | N2: Название | O2: ИНН_чист | P2: Ошибка_ИНН | Q2: КПП | R2: Телефон_чист | S2: Email_чист | T2: Ошибка_Email | U2: Индекс | V2: Адрес_остаток
A3: 1 | B3: =RAW_Поставщики!A2 -> P001 | C3: =RAW_Поставщики!B2 -> ООО ТехноСнаб | D3: =RAW_Поставщики!C2 -> 7708123456 | E3: =RAW_Поставщики!D2 -> 770801001 | F3: =RAW_Поставщики!E2 -> 8-903-123-45-67 | G3: =RAW_Поставщики!F2 -> info@tehnosnab.ru | H3: =RAW_Поставщики!G2 -> 125009 г.Москва ул.Тверская д.15 | I3: =SUBSTITUTE(SUBSTITUTE(TRIM(D3)," ",""),CHAR(160),"") -> 7708123456 | J3: =SUBSTITUTE(SUBSTITUTE(SUBSTITUTE(SUBSTITUTE(SUBSTITUTE(SUBSTITUTE(F3," ",""),"-",""),"+",""),"(",""),")",""),CHAR(160),"") -> 89031234567 | K3: =SUBSTITUTE(SUBSTITUTE(TRIM(G3)," ",""),CHAR(160),"") -> info@tehnosnab.ru | L3: =TRIM(MID(H3,8,LEN(H3))) -> г.Москва ул.Тверская д.15 | M3: =B3 -> P001 | N3: =TRIM(C3) -> ООО ТехноСнаб | O3: =IF(OR(LEN(I3)=10,LEN(I3)=12),I3,"") -> 7708123456 | P3: =IF(OR(LEN(I3)=10,LEN(I3)=12),"OK","Ошибка ИНН") -> OK | Q3: =E3 -> 770801001 | R3: =IF(LEN(J3)>=10,"+7 ("&MID(J3,LEN(J3)-9,3)&") "&MID(J3,LEN(J3)-6,3)&"-"&MID(J3,LEN(J3)-3,2)&"-"&RIGHT(J3,2),"Ошибка телефона") -> +7 (903) 123-45-67 | S3: =K3 -> info@tehnosnab.ru | T3: =IF(AND(ISNUMBER(FIND("@",K3)),ISNUMBER(FIND(".",MID(K3,FIND("@",K3),100)))),"OK","Ошибка Email") -> OK | U3: =LEFT(TRIM(H3),6) -> 125009 | V3: =L3 -> г.Москва ул.Тверская д.15
A4: 2 | B4: =RAW_Поставщики!A3 -> P002 | C4: =RAW_Поставщики!B3 -> ЗАО ЭлектроПром | D4: =RAW_Поставщики!C3 -> 7812345678123 | E4: =RAW_Поставщики!D3 -> 781201001 | F4: =RAW_Поставщики!E3 -> +7 903 234-56-78 | G4: =RAW_Поставщики!F3 -> zakaz@electroprom | H4: =RAW_Поставщики!G3 -> 191186 г.Санкт-Петербург Невский пр.д.28 | I4: =SUBSTITUTE(SUBSTITUTE(TRIM(D4)," ",""),CHAR(160),"") -> 7812345678123 | J4: =SUBSTITUTE(SUBSTITUTE(SUBSTITUTE(SUBSTITUTE(SUBSTITUTE(SUBSTITUTE(F4," ",""),"-",""),"+",""),"(",""),")",""),CHAR(160),"") -> 79032345678 | K4: =SUBSTITUTE(SUBSTITUTE(TRIM(G4)," ",""),CHAR(160),"") -> zakaz@electroprom | L4: =TRIM(MID(H4,8,LEN(H4))) -> г.Санкт-Петербург Невский пр.д.28 | M4: =B4 -> P002 | N4: =TRIM(C4) -> ЗАО ЭлектроПром | O4: =IF(OR(LEN(I4)=10,LEN(I4)=12),I4,"") | P4: =IF(OR(LEN(I4)=10,LEN(I4)=12),"OK","Ошибка ИНН") -> Ошибка ИНН | Q4: =E4 -> 781201001 | R4: =IF(LEN(J4)>=10,"+7 ("&MID(J4,LEN(J4)-9,3)&") "&MID(J4,LEN(J4)-6,3)&"-"&MID(J4,LEN(J4)-3,2)&"-"&RIGHT(J4,2),"Ошибка телефона") -> +7 (903) 234-56-78 | S4: =K4 -> zakaz@electroprom | T4: =IF(AND(ISNUMBER(FIND("@",K4)),ISNUMBER(FIND(".",MID(K4,FIND("@",K4),100)))),"OK","Ошибка Email") -> Ошибка Email | U4: =LEFT(TRIM(H4),6) -> 191186 | V4: =L4 -> г.Санкт-Петербург Невский пр.д.28
A5: 3 | B5: =RAW_Поставщики!A4 -> P003 | C5: =RAW_Поставщики!B4 -> ООО КомплектСервис | D5: =RAW_Поставщики!C4 -> 77098765 | E5: =RAW_Поставщики!D4 -> 770901001 | F5: =RAW_Поставщики!E4 -> 8 903 345 67 89 | G5: =RAW_Поставщики!F4 -> komplekt@mail.ru | H5: =RAW_Поставщики!G4 -> 127006 г.Москва ул.Петровка д.20 | I5: =SUBSTITUTE(SUBSTITUTE(TRIM(D5)," ",""),CHAR(160),"") -> 77098765 | J5: =SUBSTITUTE(SUBSTITUTE(SUBSTITUTE(SUBSTITUTE(SUBSTITUTE(SUBSTITUTE(F5," ",""),"-",""),"+",""),"(",""),")",""),CHAR(160),"") -> 89033456789 | K5: =SUBSTITUTE(SUBSTITUTE(TRIM(G5)," ",""),CHAR(160),"") -> komplekt@mail.ru | L5: =TRIM(MID(H5,8,LEN(H5))) -> г.Москва ул.Петровка д.20 | M5: =B5 -> P003 | N5: =TRIM(C5) -> ООО КомплектСервис | O5: =IF(OR(LEN(I5)=10,LEN(I5)=12),I5,"") | P5: =IF(OR(LEN(I5)=10,LEN(I5)=12),"OK","Ошибка ИНН") -> Ошибка ИНН | Q5: =E5 -> 770901001 | R5: =IF(LEN(J5)>=10,"+7 ("&MID(J5,LEN(J5)-9,3)&") "&MID(J5,LEN(J5)-6,3)&"-"&MID(J5,LEN(J5)-3,2)&"-"&RIGHT(J5,2),"Ошибка телефона") -> +7 (903) 345-67-89 | S5: =K5 -> komplekt@mail.ru | T5: =IF(AND(ISNUMBER(FIND("@",K5)),ISNUMBER(FIND(".",MID(K5,FIND("@",K5),100)))),"OK","Ошибка Email") -> OK | U5: =LEFT(TRIM(H5),6) -> 127006 | V5: =L5 -> г.Москва ул.Петровка д.20
A6: 4 | B6: =RAW_Поставщики!A5 -> P004 | C6: =RAW_Поставщики!B5 -> АО ТехноИмпорт | D6: =RAW_Поставщики!C5 -> 7712345678 | E6: =RAW_Поставщики!D5 -> 771001001 | F6: =RAW_Поставщики!E5 -> +79034567890 | G6: =RAW_Поставщики!F5 -> import@techno | H6: =RAW_Поставщики!G5 -> 119019 г.Москва ул.Арбат д.12 | I6: =SUBSTITUTE(SUBSTITUTE(TRIM(D6)," ",""),CHAR(160),"") -> 7712345678 | J6: =SUBSTITUTE(SUBSTITUTE(SUBSTITUTE(SUBSTITUTE(SUBSTITUTE(SUBSTITUTE(F6," ",""),"-",""),"+",""),"(",""),")",""),CHAR(160),"") -> 79034567890 | K6: =SUBSTITUTE(SUBSTITUTE(TRIM(G6)," ",""),CHAR(160),"") -> import@techno | L6: =TRIM(MID(H6,8,LEN(H6))) -> г.Москва ул.Арбат д.12 | M6: =B6 -> P004 | N6: =TRIM(C6) -> АО ТехноИмпорт | O6: =IF(OR(LEN(I6)=10,LEN(I6)=12),I6,"") -> 7712345678 | P6: =IF(OR(LEN(I6)=10,LEN(I6)=12),"OK","Ошибка ИНН") -> OK | Q6: =E6 -> 771001001 | R6: =IF(LEN(J6)>=10,"+7 ("&MID(J6,LEN(J6)-9,3)&") "&MID(J6,LEN(J6)-6,3)&"-"&MID(J6,LEN(J6)-3,2)&"-"&RIGHT(J6,2),"Ошибка телефона") -> +7 (903) 456-78-90 | S6: =K6 -> import@techno | T6: =IF(AND(ISNUMBER(FIND("@",K6)),ISNUMBER(FIND(".",MID(K6,FIND("@",K6),100)))),"OK","Ошибка Email") -> Ошибка Email | U6: =LEFT(TRIM(H6),6) -> 119019 | V6: =L6 -> г.Москва ул.Арбат д.12
A7: 5 | B7: =RAW_Поставщики!A6 -> P005 | C7: =RAW_Поставщики!B6 -> ООО ТоргМастер | D7: =RAW_Поставщики!C6 -> 7801234567890 | E7: =RAW_Поставщики!D6 -> 780101001 | F7: =RAW_Поставщики!E6 -> 8-903-567-89-01 | G7: =RAW_Поставщики!F6 -> torg@master | H7: =RAW_Поставщики!G6 -> 192007 г.Санкт-Петербург пр.Обуховской Обороны д.120 | I7: =SUBSTITUTE(SUBSTITUTE(TRIM(D7)," ",""),CHAR(160),"") -> 7801234567890 | J7: =SUBSTITUTE(SUBSTITUTE(SUBSTITUTE(SUBSTITUTE(SUBSTITUTE(SUBSTITUTE(F7," ",""),"-",""),"+",""),"(",""),")",""),CHAR(160),"") -> 89035678901 | K7: =SUBSTITUTE(SUBSTITUTE(TRIM(G7)," ",""),CHAR(160),"") -> torg@master | L7: =TRIM(MID(H7,8,LEN(H7))) -> г.Санкт-Петербург пр.Обуховской Обороны д.120 | M7: =B7 -> P005 | N7: =TRIM(C7) -> ООО ТоргМастер | O7: =IF(OR(LEN(I7)=10,LEN(I7)=12),I7,"") | P7: =IF(OR(LEN(I7)=10,LEN(I7)=12),"OK","Ошибка ИНН") -> Ошибка ИНН | Q7: =E7 -> 780101001 | R7: =IF(LEN(J7)>=10,"+7 ("&MID(J7,LEN(J7)-9,3)&") "&MID(J7,LEN(J7)-6,3)&"-"&MID(J7,LEN(J7)-3,2)&"-"&RIGHT(J7,2),"Ошибка телефона") -> +7 (903) 567-89-01 | S7: =K7 -> torg@master | T7: =IF(AND(ISNUMBER(FIND("@",K7)),ISNUMBER(FIND(".",MID(K7,FIND("@",K7),100)))),"OK","Ошибка Email") -> Ошибка Email | U7: =LEFT(TRIM(H7),6) -> 192007 | V7: =L7 -> г.Санкт-Петербург пр.Обуховской Обороны д.120
A8: 6 | B8: =RAW_Поставщики!A7 -> P006 | C8: =RAW_Поставщики!B7 -> ЗАО Техноресурс | D8: =RAW_Поставщики!C7 -> 77134567 | E8: =RAW_Поставщики!D7 -> 771101001 | F8: =RAW_Поставщики!E7 -> 8-903-678-90-12 | G8: =RAW_Поставщики!F7 -> resurs@techno.ru | H8: =RAW_Поставщики!G7 -> 119121 г.Москва ул.Плющиха д.25 | I8: =SUBSTITUTE(SUBSTITUTE(TRIM(D8)," ",""),CHAR(160),"") -> 77134567 | J8: =SUBSTITUTE(SUBSTITUTE(SUBSTITUTE(SUBSTITUTE(SUBSTITUTE(SUBSTITUTE(F8," ",""),"-",""),"+",""),"(",""),")",""),CHAR(160),"") -> 89036789012 | K8: =SUBSTITUTE(SUBSTITUTE(TRIM(G8)," ",""),CHAR(160),"") -> resurs@techno.ru | L8: =TRIM(MID(H8,8,LEN(H8))) -> г.Москва ул.Плющиха д.25 | M8: =B8 -> P006 | N8: =TRIM(C8) -> ЗАО Техноресурс | O8: =IF(OR(LEN(I8)=10,LEN(I8)=12),I8,"") | P8: =IF(OR(LEN(I8)=10,LEN(I8)=12),"OK","Ошибка ИНН") -> Ошибка ИНН | Q8: =E8 -> 771101001 | R8: =IF(LEN(J8)>=10,"+7 ("&MID(J8,LEN(J8)-9,3)&") "&MID(J8,LEN(J8)-6,3)&"-"&MID(J8,LEN(J8)-3,2)&"-"&RIGHT(J8,2),"Ошибка телефона") -> +7 (903) 678-90-12 | S8: =K8 -> resurs@techno.ru | T8: =IF(AND(ISNUMBER(FIND("@",K8)),ISNUMBER(FIND(".",MID(K8,FIND("@",K8),100)))),"OK","Ошибка Email") -> OK | U8: =LEFT(TRIM(H8),6) -> 119121 | V8: =L8 -> г.Москва ул.Плющиха д.25
A9: 7 | B9: =RAW_Поставщики!A8 -> P007 | C9: =RAW_Поставщики!B8 -> ООО ПрогрессПлюс | D9: =RAW_Поставщики!C8 -> 7802345678 | E9: =RAW_Поставщики!D8 -> 780201001 | F9: =RAW_Поставщики!E8 -> +7 903 789-01-23 | G9: =RAW_Поставщики!F8 -> progress@mail | H9: =RAW_Поставщики!G8 -> 197022 г.Санкт-Петербург ул.Профессора Попова д.37 | I9: =SUBSTITUTE(SUBSTITUTE(TRIM(D9)," ",""),CHAR(160),"") -> 7802345678 | J9: =SUBSTITUTE(SUBSTITUTE(SUBSTITUTE(SUBSTITUTE(SUBSTITUTE(SUBSTITUTE(F9," ",""),"-",""),"+",""),"(",""),")",""),CHAR(160),"") -> 79037890123 | K9: =SUBSTITUTE(SUBSTITUTE(TRIM(G9)," ",""),CHAR(160),"") -> progress@mail | L9: =TRIM(MID(H9,8,LEN(H9))) -> г.Санкт-Петербург ул.Профессора Попова д.37 | M9: =B9 -> P007 | N9: =TRIM(C9) -> ООО ПрогрессПлюс | O9: =IF(OR(LEN(I9)=10,LEN(I9)=12),I9,"") -> 7802345678 | P9: =IF(OR(LEN(I9)=10,LEN(I9)=12),"OK","Ошибка ИНН") -> OK | Q9: =E9 -> 780201001 | R9: =IF(LEN(J9)>=10,"+7 ("&MID(J9,LEN(J9)-9,3)&") "&MID(J9,LEN(J9)-6,3)&"-"&MID(J9,LEN(J9)-3,2)&"-"&RIGHT(J9,2),"Ошибка телефона") -> +7 (903) 789-01-23 | S9: =K9 -> progress@mail | T9: =IF(AND(ISNUMBER(FIND("@",K9)),ISNUMBER(FIND(".",MID(K9,FIND("@",K9),100)))),"OK","Ошибка Email") -> Ошибка Email | U9: =LEFT(TRIM(H9),6) -> 197022 | V9: =L9 -> г.Санкт-Петербург ул.Профессора Попова д.37
A10: 8 | B10: =RAW_Поставщики!A9 -> P008 | C10: =RAW_Поставщики!B9 -> АО ЭлектронСбыт | D10: =RAW_Поставщики!C9 -> 771456789012 | E10: =RAW_Поставщики!D9 -> 771201001 | F10: =RAW_Поставщики!E9 -> 8-903-890-12-34 | G10: =RAW_Поставщики!F9 -> electron@sbyt | H10: =RAW_Поставщики!G9 -> 109316 г.Москва ул.Таганская д.54 | I10: =SUBSTITUTE(SUBSTITUTE(TRIM(D10)," ",""),CHAR(160),"") -> 771456789012 | J10: =SUBSTITUTE(SUBSTITUTE(SUBSTITUTE(SUBSTITUTE(SUBSTITUTE(SUBSTITUTE(F10," ",""),"-",""),"+",""),"(",""),")",""),CHAR(160),"") -> 89038901234 | K10: =SUBSTITUTE(SUBSTITUTE(TRIM(G10)," ",""),CHAR(160),"") -> electron@sbyt | L10: =TRIM(MID(H10,8,LEN(H10))) -> г.Москва ул.Таганская д.54 | M10: =B10 -> P008 | N10: =TRIM(C10) -> АО ЭлектронСбыт | O10: =IF(OR(LEN(I10)=10,LEN(I10)=12),I10,"") -> 771456789012 | P10: =IF(OR(LEN(I10)=10,LEN(I10)=12),"OK","Ошибка ИНН") -> OK | Q10: =E10 -> 771201001 | R10: =IF(LEN(J10)>=10,"+7 ("&MID(J10,LEN(J10)-9,3)&") "&MID(J10,LEN(J10)-6,3)&"-"&MID(J10,LEN(J10)-3,2)&"-"&RIGHT(J10,2),"Ошибка телефона") -> +7 (903) 890-12-34 | S10: =K10 -> electron@sbyt | T10: =IF(AND(ISNUMBER(FIND("@",K10)),ISNUMBER(FIND(".",MID(K10,FIND("@",K10),100)))),"OK","Ошибка Email") -> Ошибка Email | U10: =LEFT(TRIM(H10),6) -> 109316 | V10: =L10 -> г.Москва ул.Таганская д.54
A11: 9 | B11: =RAW_Поставщики!A10 -> P009 | C11: =RAW_Поставщики!B10 -> ООО СмартТех | D11: =RAW_Поставщики!C10 -> 7803456789 | E11: =RAW_Поставщики!D10 -> 780301001 | F11: =RAW_Поставщики!E10 -> +79039012345 | G11: =RAW_Поставщики!F10 -> smart@tech | H11: =RAW_Поставщики!G10 -> 196084 г.Санкт-Петербург ул.Заставская д.22 | I11: =SUBSTITUTE(SUBSTITUTE(TRIM(D11)," ",""),CHAR(160),"") -> 7803456789 | J11: =SUBSTITUTE(SUBSTITUTE(SUBSTITUTE(SUBSTITUTE(SUBSTITUTE(SUBSTITUTE(F11," ",""),"-",""),"+",""),"(",""),")",""),CHAR(160),"") -> 79039012345 | K11: =SUBSTITUTE(SUBSTITUTE(TRIM(G11)," ",""),CHAR(160),"") -> smart@tech | L11: =TRIM(MID(H11,8,LEN(H11))) -> г.Санкт-Петербург ул.Заставская д.22 | M11: =B11 -> P009 | N11: =TRIM(C11) -> ООО СмартТех | O11: =IF(OR(LEN(I11)=10,LEN(I11)=12),I11,"") -> 7803456789 | P11: =IF(OR(LEN(I11)=10,LEN(I11)=12),"OK","Ошибка ИНН") -> OK | Q11: =E11 -> 780301001 | R11: =IF(LEN(J11)>=10,"+7 ("&MID(J11,LEN(J11)-9,3)&") "&MID(J11,LEN(J11)-6,3)&"-"&MID(J11,LEN(J11)-3,2)&"-"&RIGHT(J11,2),"Ошибка телефона") -> +7 (903) 901-23-45 | S11: =K11 -> smart@tech | T11: =IF(AND(ISNUMBER(FIND("@",K11)),ISNUMBER(FIND(".",MID(K11,FIND("@",K11),100)))),"OK","Ошибка Email") -> Ошибка Email | U11: =LEFT(TRIM(H11),6) -> 196084 | V11: =L11 -> г.Санкт-Петербург ул.Заставская д.22
A12: 10 | B12: =RAW_Поставщики!A11 -> P010 | C12: =RAW_Поставщики!B11 -> ЗАО ТехноПром | D12: =RAW_Поставщики!C11 -> 7715678901 | E12: =RAW_Поставщики!D11 -> 771301001 | F12: =RAW_Поставщики!E11 -> 8-903-012-34-56 | G12: =RAW_Поставщики!F11 -> prom@tehno | H12: =RAW_Поставщики!G11 -> 119334 г.Москва ул.Косыгина д.17 | I12: =SUBSTITUTE(SUBSTITUTE(TRIM(D12)," ",""),CHAR(160),"") -> 7715678901 | J12: =SUBSTITUTE(SUBSTITUTE(SUBSTITUTE(SUBSTITUTE(SUBSTITUTE(SUBSTITUTE(F12," ",""),"-",""),"+",""),"(",""),")",""),CHAR(160),"") -> 89030123456 | K12: =SUBSTITUTE(SUBSTITUTE(TRIM(G12)," ",""),CHAR(160),"") -> prom@tehno | L12: =TRIM(MID(H12,8,LEN(H12))) -> г.Москва ул.Косыгина д.17 | M12: =B12 -> P010 | N12: =TRIM(C12) -> ЗАО ТехноПром | O12: =IF(OR(LEN(I12)=10,LEN(I12)=12),I12,"") -> 7715678901 | P12: =IF(OR(LEN(I12)=10,LEN(I12)=12),"OK","Ошибка ИНН") -> OK | Q12: =E12 -> 771301001 | R12: =IF(LEN(J12)>=10,"+7 ("&MID(J12,LEN(J12)-9,3)&") "&MID(J12,LEN(J12)-6,3)&"-"&MID(J12,LEN(J12)-3,2)&"-"&RIGHT(J12,2),"Ошибка телефона") -> +7 (903) 012-34-56 | S12: =K12 -> prom@tehno | T12: =IF(AND(ISNUMBER(FIND("@",K12)),ISNUMBER(FIND(".",MID(K12,FIND("@",K12),100)))),"OK","Ошибка Email") -> Ошибка Email | U12: =LEFT(TRIM(H12),6) -> 119334 | V12: =L12 -> г.Москва ул.Косыгина д.17
A13: 11 | B13: =RAW_Поставщики!A12 -> P011 | C13: =RAW_Поставщики!B12 -> ООО СервисПлюс | D13: =RAW_Поставщики!C12 -> 78045678 | E13: =RAW_Поставщики!D12 -> 780401001 | F13: =RAW_Поставщики!E12 -> 8-903-123-45-67 | G13: =RAW_Поставщики!F12 -> service@plus.ru | H13: =RAW_Поставщики!G12 -> 199178 г.Санкт-Петербург ул.Средний пр.В.О.д.78 | I13: =SUBSTITUTE(SUBSTITUTE(TRIM(D13)," ",""),CHAR(160),"") -> 78045678 | J13: =SUBSTITUTE(SUBSTITUTE(SUBSTITUTE(SUBSTITUTE(SUBSTITUTE(SUBSTITUTE(F13," ",""),"-",""),"+",""),"(",""),")",""),CHAR(160),"") -> 89031234567 | K13: =SUBSTITUTE(SUBSTITUTE(TRIM(G13)," ",""),CHAR(160),"") -> service@plus.ru | L13: =TRIM(MID(H13,8,LEN(H13))) -> г.Санкт-Петербург ул.Средний пр.В.О.д.78 | M13: =B13 -> P011 | N13: =TRIM(C13) -> ООО СервисПлюс | O13: =IF(OR(LEN(I13)=10,LEN(I13)=12),I13,"") | P13: =IF(OR(LEN(I13)=10,LEN(I13)=12),"OK","Ошибка ИНН") -> Ошибка ИНН | Q13: =E13 -> 780401001 | R13: =IF(LEN(J13)>=10,"+7 ("&MID(J13,LEN(J13)-9,3)&") "&MID(J13,LEN(J13)-6,3)&"-"&MID(J13,LEN(J13)-3,2)&"-"&RIGHT(J13,2),"Ошибка телефона") -> +7 (903) 123-45-67 | S13: =K13 -> service@plus.ru | T13: =IF(AND(ISNUMBER(FIND("@",K13)),ISNUMBER(FIND(".",MID(K13,FIND("@",K13),100)))),"OK","Ошибка Email") -> OK | U13: =LEFT(TRIM(H13),6) -> 199178 | V13: =L13 -> г.Санкт-Петербург ул.Средний пр.В.О.д.78
A14: 12 | B14: =RAW_Поставщики!A13 -> P012 | C14: =RAW_Поставщики!B13 -> АО ТехноТрейд | D14: =RAW_Поставщики!C13 -> 7716789012 | E14: =RAW_Поставщики!D13 -> 771401001 | F14: =RAW_Поставщики!E13 -> 89032345678 | G14: =RAW_Поставщики!F13 -> trade@tehno | H14: =RAW_Поставщики!G13 -> 107113 г.Москва ул.Сокольнический вал д.3 | I14: =SUBSTITUTE(SUBSTITUTE(TRIM(D14)," ",""),CHAR(160),"") -> 7716789012 | J14: =SUBSTITUTE(SUBSTITUTE(SUBSTITUTE(SUBSTITUTE(SUBSTITUTE(SUBSTITUTE(F14," ",""),"-",""),"+",""),"(",""),")",""),CHAR(160),"") -> 89032345678 | K14: =SUBSTITUTE(SUBSTITUTE(TRIM(G14)," ",""),CHAR(160),"") -> trade@tehno | L14: =TRIM(MID(H14,8,LEN(H14))) -> г.Москва ул.Сокольнический вал д.3 | M14: =B14 -> P012 | N14: =TRIM(C14) -> АО ТехноТрейд | O14: =IF(OR(LEN(I14)=10,LEN(I14)=12),I14,"") -> 7716789012 | P14: =IF(OR(LEN(I14)=10,LEN(I14)=12),"OK","Ошибка ИНН") -> OK | Q14: =E14 -> 771401001 | R14: =IF(LEN(J14)>=10,"+7 ("&MID(J14,LEN(J14)-9,3)&") "&MID(J14,LEN(J14)-6,3)&"-"&MID(J14,LEN(J14)-3,2)&"-"&RIGHT(J14,2),"Ошибка телефона") -> +7 (903) 234-56-78 | S14: =K14 -> trade@tehno | T14: =IF(AND(ISNUMBER(FIND("@",K14)),ISNUMBER(FIND(".",MID(K14,FIND("@",K14),100)))),"OK","Ошибка Email") -> Ошибка Email | U14: =LEFT(TRIM(H14),6) -> 107113 | V14: =L14 -> г.Москва ул.Сокольнический вал д.3
... A52: 50 | B52: =RAW_Поставщики!A51 -> P050 | C52: =RAW_Поставщики!B51 -> ЗАО ТехноПроект | D52: =RAW_Поставщики!C51 -> 7735678901 | E52: =RAW_Поставщики!D51 -> 773301001 | F52: =RAW_Поставщики!E51 -> 8-903-012-34-56 | G52: =RAW_Поставщики!F51 -> proekt@tehno | H52: =RAW_Поставщики!G51 -> 119435 г.Москва ул.Погодинская д.18 | I52: =SUBSTITUTE(SUBSTITUTE(TRIM(D52)," ",""),CHAR(160),"") -> 7735678901 | J52: =SUBSTITUTE(SUBSTITUTE(SUBSTITUTE(SUBSTITUTE(SUBSTITUTE(SUBSTITUTE(F52," ",""),"-",""),"+",""),"(",""),")",""),CHAR(160),"") -> 89030123456 | K52: =SUBSTITUTE(SUBSTITUTE(TRIM(G52)," ",""),CHAR(160),"") -> proekt@tehno | L52: =TRIM(MID(H52,8,LEN(H52))) -> г.Москва ул.Погодинская д.18 | M52: =B52 -> P050 | N52: =TRIM(C52) -> ЗАО ТехноПроект | O52: =IF(OR(LEN(I52)=10,LEN(I52)=12),I52,"") -> 7735678901 | P52: =IF(OR(LEN(I52)=10,LEN(I52)=12),"OK","Ошибка ИНН") -> OK | Q52: =E52 -> 773301001 | R52: =IF(LEN(J52)>=10,"+7 ("&MID(J52,LEN(J52)-9,3)&") "&MID(J52,LEN(J52)-6,3)&"-"&MID(J52,LEN(J52)-3,2)&"-"&RIGHT(J52,2),"Ошибка телефона") -> +7 (903) 012-34-56 | S52: =K52 -> proekt@tehno | T52: =IF(AND(ISNUMBER(FIND("@",K52)),ISNUMBER(FIND(".",MID(K52,FIND("@",K52),100)))),"OK","Ошибка Email") -> Ошибка Email | U52: =LEFT(TRIM(H52),6) -> 119435 | V52: =L52 -> г.Москва ул.Погодинская д.18

Sheet Продажи_очищенные
A1: ЭТАП 3 — Очистка продаж (даты, количество, валюты, статусы, дубликаты, связывание с каталогом)
A2: № | B2: Дата (ориг.) | C2: Артикул (ориг.) | D2: Кол-во (ориг.) | E2: Цена_прод (ориг.) | F2: ID_клиента | G2: ID_поставщика | H2: Статус (ориг.) | I2: Артикул_без_преф | J2: Символ_валюты | K2: Число_цены | L2: Дата | M2: Артикул_чист | N2: Количество | O2: Валюта | P2: Цена_продажи_руб | Q2: Статус_чист | R2: Розн_цена_из_каталога | S2: Категория_из_каталога | T2: Проверка_цены_продажи | U2: Ключ_дубля | V2: Признак_дубля
A3: 1 | B3: =RAW_Продажи!A2 -> 01/15/2025 | C3: =RAW_Продажи!B2 -> №АРТ-045 | D3: =RAW_Продажи!C2 -> 2 | E3: =RAW_Продажи!D2 -> $100 | F3: =RAW_Продажи!E2 -> C0001 | G3: =RAW_Продажи!F2 -> P012 | H3: =RAW_Продажи!G2 -> Завершен | I3: =SUBSTITUTE(SUBSTITUTE(C3,"№АРТ-",""),"АРТ_","") -> 045 | J3: =IF(LEFT(TRIM(E3),1)="$","$",IF(LEFT(TRIM(E3),1)="€","€","₽")) -> $ | K3: =VALUE(SUBSTITUTE(SUBSTITUTE(SUBSTITUTE(SUBSTITUTE(TRIM(E3),"$",""),"€",""),"₽","")," ","")) -> 100 | L3: =DATE(VALUE(MID(B3,7,4)),VALUE(LEFT(B3,2)),VALUE(MID(B3,4,2))) -> 45672 | M3: ="АРТ-"&LEFT(I3,3) -> АРТ-045 | N3: =VALUE(LEFT(TRIM(D3),FIND(" ",TRIM(D3)&" ")-1)) -> 2 | O3: =IFERROR(VLOOKUP(J3,Справочники!$G$6:$H$8,2,0),"RUB") -> USD | P3: =ROUND(K3*IFERROR(VLOOKUP(J3,Справочники!$G$6:$I$8,3,0),1),2) -> 9500 | Q3: =IFERROR(VLOOKUP(H3,Справочники!$D$6:$E$14,2,0),"НЕИЗВЕСТНО") -> Завершен | R3: =IFERROR(INDEX(Товары_очищенные!$Q$3:$Q$503,MATCH(M3,Товары_очищенные!$L$3:$L$503,0)),"нет в каталоге") -> 137000 | S3: =IFERROR(INDEX(Товары_очищенные!$N$3:$N$503,MATCH(M3,Товары_очищенные!$L$3:$L$503,0)),"нет в каталоге") -> Телевизоры | T3: =IF(ISNUMBER(R3),IF(P3<=R3*1.5,"OK","Цена выше розницы"),"—") -> OK | U3: =TEXT(L3,"DD.MM.YYYY")&"|"&M3&"|"&F3 -> 15/01/2025|АРТ-045|C0001 | V3: =IF(COUNTIF($U$3:U3,U3)>1,"ДУБЛЬ","оригинал") -> оригинал
A4: 2 | B4: =RAW_Продажи!A3 -> 01/15/2025 | C4: =RAW_Продажи!B3 -> АРТ_112 | D4: =RAW_Продажи!C3 -> 1 | E4: =RAW_Продажи!D3 -> €85 | F4: =RAW_Продажи!E3 -> C0002 | G4: =RAW_Продажи!F3 -> P007 | H4: =RAW_Продажи!G3 -> завершен | I4: =SUBSTITUTE(SUBSTITUTE(C4,"№АРТ-",""),"АРТ_","") -> 112 | J4: =IF(LEFT(TRIM(E4),1)="$","$",IF(LEFT(TRIM(E4),1)="€","€","₽")) -> € | K4: =VALUE(SUBSTITUTE(SUBSTITUTE(SUBSTITUTE(SUBSTITUTE(TRIM(E4),"$",""),"€",""),"₽","")," ","")) -> 85 | L4: =DATE(VALUE(MID(B4,7,4)),VALUE(LEFT(B4,2)),VALUE(MID(B4,4,2))) -> 45672 | M4: ="АРТ-"&LEFT(I4,3) -> АРТ-112 | N4: =VALUE(LEFT(TRIM(D4),FIND(" ",TRIM(D4)&" ")-1)) -> 1 | O4: =IFERROR(VLOOKUP(J4,Справочники!$G$6:$H$8,2,0),"RUB") -> EUR | P4: =ROUND(K4*IFERROR(VLOOKUP(J4,Справочники!$G$6:$I$8,3,0),1),2) -> 8500 | Q4: =IFERROR(VLOOKUP(H4,Справочники!$D$6:$E$14,2,0),"НЕИЗВЕСТНО") -> Завершен | R4: =IFERROR(INDEX(Товары_очищенные!$Q$3:$Q$503,MATCH(M4,Товары_очищенные!$L$3:$L$503,0)),"нет в каталоге") -> 34990 | S4: =IFERROR(INDEX(Товары_очищенные!$N$3:$N$503,MATCH(M4,Товары_очищенные!$L$3:$L$503,0)),"нет в каталоге") -> Наушники | T4: =IF(ISNUMBER(R4),IF(P4<=R4*1.5,"OK","Цена выше розницы"),"—") -> OK | U4: =TEXT(L4,"DD.MM.YYYY")&"|"&M4&"|"&F4 -> 15/01/2025|АРТ-112|C0002 | V4: =IF(COUNTIF($U$3:U4,U4)>1,"ДУБЛЬ","оригинал") -> оригинал
A5: 3 | B5: =RAW_Продажи!A4 -> 01/16/2025 | C5: =RAW_Продажи!B4 -> 003/24 | D5: =RAW_Продажи!C4 -> 3 шт. | E5: =RAW_Продажи!D4 -> 7500 ₽ | F5: =RAW_Продажи!E4 -> C0003 | G5: =RAW_Продажи!F4 -> P023 | H5: =RAW_Продажи!G4 -> completed | I5: =SUBSTITUTE(SUBSTITUTE(C5,"№АРТ-",""),"АРТ_","") -> 003/24 | J5: =IF(LEFT(TRIM(E5),1)="$","$",IF(LEFT(TRIM(E5),1)="€","€","₽")) -> ₽ | K5: =VALUE(SUBSTITUTE(SUBSTITUTE(SUBSTITUTE(SUBSTITUTE(TRIM(E5),"$",""),"€",""),"₽","")," ","")) -> 7500 | L5: =DATE(VALUE(MID(B5,7,4)),VALUE(LEFT(B5,2)),VALUE(MID(B5,4,2))) -> 45673 | M5: ="АРТ-"&LEFT(I5,3) -> АРТ-003 | N5: =VALUE(LEFT(TRIM(D5),FIND(" ",TRIM(D5)&" ")-1)) -> 3 | O5: =IFERROR(VLOOKUP(J5,Справочники!$G$6:$H$8,2,0),"RUB") -> RUB | P5: =ROUND(K5*IFERROR(VLOOKUP(J5,Справочники!$G$6:$I$8,3,0),1),2) -> 7500 | Q5: =IFERROR(VLOOKUP(H5,Справочники!$D$6:$E$14,2,0),"НЕИЗВЕСТНО") -> Завершен | R5: =IFERROR(INDEX(Товары_очищенные!$Q$3:$Q$503,MATCH(M5,Товары_очищенные!$L$3:$L$503,0)),"нет в каталоге") -> 77700 | S5: =IFERROR(INDEX(Товары_очищенные!$N$3:$N$503,MATCH(M5,Товары_очищенные!$L$3:$L$503,0)),"нет в каталоге") -> Смартфоны | T5: =IF(ISNUMBER(R5),IF(P5<=R5*1.5,"OK","Цена выше розницы"),"—") -> OK | U5: =TEXT(L5,"DD.MM.YYYY")&"|"&M5&"|"&F5 -> 16/01/2025|АРТ-003|C0003 | V5: =IF(COUNTIF($U$3:U5,U5)>1,"ДУБЛЬ","оригинал") -> оригинал
A6: 4 | B6: =RAW_Продажи!A5 -> 01/16/2025 | C6: =RAW_Продажи!B5 -> №АРТ-234 | D6: =RAW_Продажи!C5 -> -1 | E6: =RAW_Продажи!D5 -> $110 | F6: =RAW_Продажи!E5 -> C0004 | G6: =RAW_Продажи!F5 -> P045 | H6: =RAW_Продажи!G5 -> отменен | I6: =SUBSTITUTE(SUBSTITUTE(C6,"№АРТ-",""),"АРТ_","") -> 234 | J6: =IF(LEFT(TRIM(E6),1)="$","$",IF(LEFT(TRIM(E6),1)="€","€","₽")) -> $ | K6: =VALUE(SUBSTITUTE(SUBSTITUTE(SUBSTITUTE(SUBSTITUTE(TRIM(E6),"$",""),"€",""),"₽","")," ","")) -> 110 | L6: =DATE(VALUE(MID(B6,7,4)),VALUE(LEFT(B6,2)),VALUE(MID(B6,4,2))) -> 45673 | M6: ="АРТ-"&LEFT(I6,3) -> АРТ-234 | N6: =VALUE(LEFT(TRIM(D6),FIND(" ",TRIM(D6)&" ")-1)) -> -1 | O6: =IFERROR(VLOOKUP(J6,Справочники!$G$6:$H$8,2,0),"RUB") -> USD | P6: =ROUND(K6*IFERROR(VLOOKUP(J6,Справочники!$G$6:$I$8,3,0),1),2) -> 10450 | Q6: =IFERROR(VLOOKUP(H6,Справочники!$D$6:$E$14,2,0),"НЕИЗВЕСТНО") -> Отменен | R6: =IFERROR(INDEX(Товары_очищенные!$Q$3:$Q$503,MATCH(M6,Товары_очищенные!$L$3:$L$503,0)),"нет в каталоге") -> 44500 | S6: =IFERROR(INDEX(Товары_очищенные!$N$3:$N$503,MATCH(M6,Товары_очищенные!$L$3:$L$503,0)),"нет в каталоге") -> Смартфоны | T6: =IF(ISNUMBER(R6),IF(P6<=R6*1.5,"OK","Цена выше розницы"),"—") -> OK | U6: =TEXT(L6,"DD.MM.YYYY")&"|"&M6&"|"&F6 -> 16/01/2025|АРТ-234|C0004 | V6: =IF(COUNTIF($U$3:U6,U6)>1,"ДУБЛЬ","оригинал") -> оригинал
A7: 5 | B7: =RAW_Продажи!A6 -> 01/17/2025 | C7: =RAW_Продажи!B6 -> АРТ_067 | D7: =RAW_Продажи!C6 -> 2 шт | E7: =RAW_Продажи!D6 -> €90 | F7: =RAW_Продажи!E6 -> C0005 | G7: =RAW_Продажи!F6 -> P008 | H7: =RAW_Продажи!G6 -> canceled | I7: =SUBSTITUTE(SUBSTITUTE(C7,"№АРТ-",""),"АРТ_","") -> 067 | J7: =IF(LEFT(TRIM(E7),1)="$","$",IF(LEFT(TRIM(E7),1)="€","€","₽")) -> € | K7: =VALUE(SUBSTITUTE(SUBSTITUTE(SUBSTITUTE(SUBSTITUTE(TRIM(E7),"$",""),"€",""),"₽","")," ","")) -> 90 | L7: =DATE(VALUE(MID(B7,7,4)),VALUE(LEFT(B7,2)),VALUE(MID(B7,4,2))) -> 45674 | M7: ="АРТ-"&LEFT(I7,3) -> АРТ-067 | N7: =VALUE(LEFT(TRIM(D7),FIND(" ",TRIM(D7)&" ")-1)) -> 2 | O7: =IFERROR(VLOOKUP(J7,Справочники!$G$6:$H$8,2,0),"RUB") -> EUR | P7: =ROUND(K7*IFERROR(VLOOKUP(J7,Справочники!$G$6:$I$8,3,0),1),2) -> 9000 | Q7: =IFERROR(VLOOKUP(H7,Справочники!$D$6:$E$14,2,0),"НЕИЗВЕСТНО") -> Отменен | R7: =IFERROR(INDEX(Товары_очищенные!$Q$3:$Q$503,MATCH(M7,Товары_очищенные!$L$3:$L$503,0)),"нет в каталоге") -> 109999 | S7: =IFERROR(INDEX(Товары_очищенные!$N$3:$N$503,MATCH(M7,Товары_очищенные!$L$3:$L$503,0)),"нет в каталоге") -> Телевизоры | T7: =IF(ISNUMBER(R7),IF(P7<=R7*1.5,"OK","Цена выше розницы"),"—") -> OK | U7: =TEXT(L7,"DD.MM.YYYY")&"|"&M7&"|"&F7 -> 17/01/2025|АРТ-067|C0005 | V7: =IF(COUNTIF($U$3:U7,U7)>1,"ДУБЛЬ","оригинал") -> оригинал
A8: 6 | B8: =RAW_Продажи!A7 -> 01/17/2025 | C8: =RAW_Продажи!B7 -> 078-24 | D8: =RAW_Продажи!C7 -> 1 | E8: =RAW_Продажи!D7 -> 8000 ₽ | F8: =RAW_Продажи!E7 -> C0006 | G8: =RAW_Продажи!F7 -> P031 | H8: =RAW_Продажи!G7 -> возврат | I8: =SUBSTITUTE(SUBSTITUTE(C8,"№АРТ-",""),"АРТ_","") -> 078-24 | J8: =IF(LEFT(TRIM(E8),1)="$","$",IF(LEFT(TRIM(E8),1)="€","€","₽")) -> ₽ | K8: =VALUE(SUBSTITUTE(SUBSTITUTE(SUBSTITUTE(SUBSTITUTE(TRIM(E8),"$",""),"€",""),"₽","")," ","")) -> 8000 | L8: =DATE(VALUE(MID(B8,7,4)),VALUE(LEFT(B8,2)),VALUE(MID(B8,4,2))) -> 45674 | M8: ="АРТ-"&LEFT(I8,3) -> АРТ-078 | N8: =VALUE(LEFT(TRIM(D8),FIND(" ",TRIM(D8)&" ")-1)) -> 1 | O8: =IFERROR(VLOOKUP(J8,Справочники!$G$6:$H$8,2,0),"RUB") -> RUB | P8: =ROUND(K8*IFERROR(VLOOKUP(J8,Справочники!$G$6:$I$8,3,0),1),2) -> 8000 | Q8: =IFERROR(VLOOKUP(H8,Справочники!$D$6:$E$14,2,0),"НЕИЗВЕСТНО") -> Возврат | R8: =IFERROR(INDEX(Товары_очищенные!$Q$3:$Q$503,MATCH(M8,Товары_очищенные!$L$3:$L$503,0)),"нет в каталоге") -> 13500 | S8: =IFERROR(INDEX(Товары_очищенные!$N$3:$N$503,MATCH(M8,Товары_очищенные!$L$3:$L$503,0)),"нет в каталоге") -> Аксессуары | T8: =IF(ISNUMBER(R8),IF(P8<=R8*1.5,"OK","Цена выше розницы"),"—") -> OK | U8: =TEXT(L8,"DD.MM.YYYY")&"|"&M8&"|"&F8 -> 17/01/2025|АРТ-078|C0006 | V8: =IF(COUNTIF($U$3:U8,U8)>1,"ДУБЛЬ","оригинал") -> оригинал
A9: 7 | B9: =RAW_Продажи!A8 -> 01/18/2025 | C9: =RAW_Продажи!B8 -> №АРТ-389 | D9: =RAW_Продажи!C8 -> 3 | E9: =RAW_Продажи!D8 -> $105 | F9: =RAW_Продажи!E8 -> C0007 | G9: =RAW_Продажи!F8 -> P019 | H9: =RAW_Продажи!G8 -> Завершен | I9: =SUBSTITUTE(SUBSTITUTE(C9,"№АРТ-",""),"АРТ_","") -> 389 | J9: =IF(LEFT(TRIM(E9),1)="$","$",IF(LEFT(TRIM(E9),1)="€","€","₽")) -> $ | K9: =VALUE(SUBSTITUTE(SUBSTITUTE(SUBSTITUTE(SUBSTITUTE(TRIM(E9),"$",""),"€",""),"₽","")," ","")) -> 105 | L9: =DATE(VALUE(MID(B9,7,4)),VALUE(LEFT(B9,2)),VALUE(MID(B9,4,2))) -> 45675 | M9: ="АРТ-"&LEFT(I9,3) -> АРТ-389 | N9: =VALUE(LEFT(TRIM(D9),FIND(" ",TRIM(D9)&" ")-1)) -> 3 | O9: =IFERROR(VLOOKUP(J9,Справочники!$G$6:$H$8,2,0),"RUB") -> USD | P9: =ROUND(K9*IFERROR(VLOOKUP(J9,Справочники!$G$6:$I$8,3,0),1),2) -> 9975 | Q9: =IFERROR(VLOOKUP(H9,Справочники!$D$6:$E$14,2,0),"НЕИЗВЕСТНО") -> Завершен | R9: =IFERROR(INDEX(Товары_очищенные!$Q$3:$Q$503,MATCH(M9,Товары_очищенные!$L$3:$L$503,0)),"нет в каталоге") -> 75000 | S9: =IFERROR(INDEX(Товары_очищенные!$N$3:$N$503,MATCH(M9,Товары_очищенные!$L$3:$L$503,0)),"нет в каталоге") -> Телевизоры | T9: =IF(ISNUMBER(R9),IF(P9<=R9*1.5,"OK","Цена выше розницы"),"—") -> OK | U9: =TEXT(L9,"DD.MM.YYYY")&"|"&M9&"|"&F9 -> 18/01/2025|АРТ-389|C0007 | V9: =IF(COUNTIF($U$3:U9,U9)>1,"ДУБЛЬ","оригинал") -> оригинал
A10: 8 | B10: =RAW_Продажи!A9 -> 01/18/2025 | C10: =RAW_Продажи!B9 -> АРТ_156 | D10: =RAW_Продажи!C9 -> 2 | E10: =RAW_Продажи!D9 -> €95 | F10: =RAW_Продажи!E9 -> C0008 | G10: =RAW_Продажи!F9 -> P042 | H10: =RAW_Продажи!G9 -> completed | I10: =SUBSTITUTE(SUBSTITUTE(C10,"№АРТ-",""),"АРТ_","") -> 156 | J10: =IF(LEFT(TRIM(E10),1)="$","$",IF(LEFT(TRIM(E10),1)="€","€","₽")) -> € | K10: =VALUE(SUBSTITUTE(SUBSTITUTE(SUBSTITUTE(SUBSTITUTE(TRIM(E10),"$",""),"€",""),"₽","")," ","")) -> 95 | L10: =DATE(VALUE(MID(B10,7,4)),VALUE(LEFT(B10,2)),VALUE(MID(B10,4,2))) -> 45675 | M10: ="АРТ-"&LEFT(I10,3) -> АРТ-156 | N10: =VALUE(LEFT(TRIM(D10),FIND(" ",TRIM(D10)&" ")-1)) -> 2 | O10: =IFERROR(VLOOKUP(J10,Справочники!$G$6:$H$8,2,0),"RUB") -> EUR | P10: =ROUND(K10*IFERROR(VLOOKUP(J10,Справочники!$G$6:$I$8,3,0),1),2) -> 9500 | Q10: =IFERROR(VLOOKUP(H10,Справочники!$D$6:$E$14,2,0),"НЕИЗВЕСТНО") -> Завершен | R10: =IFERROR(INDEX(Товары_очищенные!$Q$3:$Q$503,MATCH(M10,Товары_очищенные!$L$3:$L$503,0)),"нет в каталоге") -> 17800 | S10: =IFERROR(INDEX(Товары_очищенные!$N$3:$N$503,MATCH(M10,Товары_очищенные!$L$3:$L$503,0)),"нет в каталоге") -> Наушники | T10: =IF(ISNUMBER(R10),IF(P10<=R10*1.5,"OK","Цена выше розницы"),"—") -> OK | U10: =TEXT(L10,"DD.MM.YYYY")&"|"&M10&"|"&F10 -> 18/01/2025|АРТ-156|C0008 | V10: =IF(COUNTIF($U$3:U10,U10)>1,"ДУБЛЬ","оригинал") -> оригинал
A11: 9 | B11: =RAW_Продажи!A10 -> 01/19/2025 | C11: =RAW_Продажи!B10 -> 251/24 | D11: =RAW_Продажи!C10 -> 1 шт. | E11: =RAW_Продажи!D10 -> 6500 ₽ | F11: =RAW_Продажи!E10 -> C0009 | G11: =RAW_Продажи!F10 -> P005 | H11: =RAW_Продажи!G10 -> завершен | I11: =SUBSTITUTE(SUBSTITUTE(C11,"№АРТ-",""),"АРТ_","") -> 251/24 | J11: =IF(LEFT(TRIM(E11),1)="$","$",IF(LEFT(TRIM(E11),1)="€","€","₽")) -> ₽ | K11: =VALUE(SUBSTITUTE(SUBSTITUTE(SUBSTITUTE(SUBSTITUTE(TRIM(E11),"$",""),"€",""),"₽","")," ","")) -> 6500 | L11: =DATE(VALUE(MID(B11,7,4)),VALUE(LEFT(B11,2)),VALUE(MID(B11,4,2))) -> 45676 | M11: ="АРТ-"&LEFT(I11,3) -> АРТ-251 | N11: =VALUE(LEFT(TRIM(D11),FIND(" ",TRIM(D11)&" ")-1)) -> 1 | O11: =IFERROR(VLOOKUP(J11,Справочники!$G$6:$H$8,2,0),"RUB") -> RUB | P11: =ROUND(K11*IFERROR(VLOOKUP(J11,Справочники!$G$6:$I$8,3,0),1),2) -> 6500 | Q11: =IFERROR(VLOOKUP(H11,Справочники!$D$6:$E$14,2,0),"НЕИЗВЕСТНО") -> Завершен | R11: =IFERROR(INDEX(Товары_очищенные!$Q$3:$Q$503,MATCH(M11,Товары_очищенные!$L$3:$L$503,0)),"нет в каталоге") -> 53500 | S11: =IFERROR(INDEX(Товары_очищенные!$N$3:$N$503,MATCH(M11,Товары_очищенные!$L$3:$L$503,0)),"нет в каталоге") -> Часы | T11: =IF(ISNUMBER(R11),IF(P11<=R11*1.5,"OK","Цена выше розницы"),"—") -> OK | U11: =TEXT(L11,"DD.MM.YYYY")&"|"&M11&"|"&F11 -> 19/01/2025|АРТ-251|C0009 | V11: =IF(COUNTIF($U$3:U11,U11)>1,"ДУБЛЬ","оригинал") -> оригинал
A12: 10 | B12: =RAW_Продажи!A11 -> 01/19/2025 | C12: =RAW_Продажи!B11 -> №АРТ-023 | D12: =RAW_Продажи!C11 -> -2 | E12: =RAW_Продажи!D11 -> $115 | F12: =RAW_Продажи!E11 -> C0010 | G12: =RAW_Продажи!F11 -> P036 | H12: =RAW_Продажи!G11 -> Отменен | I12: =SUBSTITUTE(SUBSTITUTE(C12,"№АРТ-",""),"АРТ_","") -> 023 | J12: =IF(LEFT(TRIM(E12),1)="$","$",IF(LEFT(TRIM(E12),1)="€","€","₽")) -> $ | K12: =VALUE(SUBSTITUTE(SUBSTITUTE(SUBSTITUTE(SUBSTITUTE(TRIM(E12),"$",""),"€",""),"₽","")," ","")) -> 115 | L12: =DATE(VALUE(MID(B12,7,4)),VALUE(LEFT(B12,2)),VALUE(MID(B12,4,2))) -> 45676 | M12: ="АРТ-"&LEFT(I12,3) -> АРТ-023 | N12: =VALUE(LEFT(TRIM(D12),FIND(" ",TRIM(D12)&" ")-1)) -> -2 | O12: =IFERROR(VLOOKUP(J12,Справочники!$G$6:$H$8,2,0),"RUB") -> USD | P12: =ROUND(K12*IFERROR(VLOOKUP(J12,Справочники!$G$6:$I$8,3,0),1),2) -> 10925 | Q12: =IFERROR(VLOOKUP(H12,Справочники!$D$6:$E$14,2,0),"НЕИЗВЕСТНО") -> Отменен | R12: =IFERROR(INDEX(Товары_очищенные!$Q$3:$Q$503,MATCH(M12,Товары_очищенные!$L$3:$L$503,0)),"нет в каталоге") -> 58500 | S12: =IFERROR(INDEX(Товары_очищенные!$N$3:$N$503,MATCH(M12,Товары_очищенные!$L$3:$L$503,0)),"нет в каталоге") -> Смартфоны | T12: =IF(ISNUMBER(R12),IF(P12<=R12*1.5,"OK","Цена выше розницы"),"—") -> OK | U12: =TEXT(L12,"DD.MM.YYYY")&"|"&M12&"|"&F12 -> 19/01/2025|АРТ-023|C0010 | V12: =IF(COUNTIF($U$3:U12,U12)>1,"ДУБЛЬ","оригинал") -> оригинал
A13: 11 | B13: =RAW_Продажи!A12 -> 01/20/2025 | C13: =RAW_Продажи!B12 -> АРТ_478 | D13: =RAW_Продажи!C12 -> 3 | E13: =RAW_Продажи!D12 -> €80 | F13: =RAW_Продажи!E12 -> C0011 | G13: =RAW_Продажи!F12 -> P014 | H13: =RAW_Продажи!G12 -> возврат | I13: =SUBSTITUTE(SUBSTITUTE(C13,"№АРТ-",""),"АРТ_","") -> 478 | J13: =IF(LEFT(TRIM(E13),1)="$","$",IF(LEFT(TRIM(E13),1)="€","€","₽")) -> € | K13: =VALUE(SUBSTITUTE(SUBSTITUTE(SUBSTITUTE(SUBSTITUTE(TRIM(E13),"$",""),"€",""),"₽","")," ","")) -> 80 | L13: =DATE(VALUE(MID(B13,7,4)),VALUE(LEFT(B13,2)),VALUE(MID(B13,4,2))) -> 45677 | M13: ="АРТ-"&LEFT(I13,3) -> АРТ-478 | N13: =VALUE(LEFT(TRIM(D13),FIND(" ",TRIM(D13)&" ")-1)) -> 3 | O13: =IFERROR(VLOOKUP(J13,Справочники!$G$6:$H$8,2,0),"RUB") -> EUR | P13: =ROUND(K13*IFERROR(VLOOKUP(J13,Справочники!$G$6:$I$8,3,0),1),2) -> 8000 | Q13: =IFERROR(VLOOKUP(H13,Справочники!$D$6:$E$14,2,0),"НЕИЗВЕСТНО") -> Возврат | R13: =IFERROR(INDEX(Товары_очищенные!$Q$3:$Q$503,MATCH(M13,Товары_очищенные!$L$3:$L$503,0)),"нет в каталоге") -> 12990 | S13: =IFERROR(INDEX(Товары_очищенные!$N$3:$N$503,MATCH(M13,Товары_очищенные!$L$3:$L$503,0)),"нет в каталоге") -> Аксессуары | T13: =IF(ISNUMBER(R13),IF(P13<=R13*1.5,"OK","Цена выше розницы"),"—") -> OK | U13: =TEXT(L13,"DD.MM.YYYY")&"|"&M13&"|"&F13 -> 20/01/2025|АРТ-478|C0011 | V13: =IF(COUNTIF($U$3:U13,U13)>1,"ДУБЛЬ","оригинал") -> оригинал
A14: 12 | B14: =RAW_Продажи!A13 -> 01/20/2025 | C14: =RAW_Продажи!B13 -> 045-24 | D14: =RAW_Продажи!C13 -> 1 | E14: =RAW_Продажи!D13 -> 8500 ₽ | F14: =RAW_Продажи!E13 -> C0012 | G14: =RAW_Продажи!F13 -> P028 | H14: =RAW_Продажи!G13 -> Завершен | I14: =SUBSTITUTE(SUBSTITUTE(C14,"№АРТ-",""),"АРТ_","") -> 045-24 | J14: =IF(LEFT(TRIM(E14),1)="$","$",IF(LEFT(TRIM(E14),1)="€","€","₽")) -> ₽ | K14: =VALUE(SUBSTITUTE(SUBSTITUTE(SUBSTITUTE(SUBSTITUTE(TRIM(E14),"$",""),"€",""),"₽","")," ","")) -> 8500 | L14: =DATE(VALUE(MID(B14,7,4)),VALUE(LEFT(B14,2)),VALUE(MID(B14,4,2))) -> 45677 | M14: ="АРТ-"&LEFT(I14,3) -> АРТ-045 | N14: =VALUE(LEFT(TRIM(D14),FIND(" ",TRIM(D14)&" ")-1)) -> 1 | O14: =IFERROR(VLOOKUP(J14,Справочники!$G$6:$H$8,2,0),"RUB") -> RUB | P14: =ROUND(K14*IFERROR(VLOOKUP(J14,Справочники!$G$6:$I$8,3,0),1),2) -> 8500 | Q14: =IFERROR(VLOOKUP(H14,Справочники!$D$6:$E$14,2,0),"НЕИЗВЕСТНО") -> Завершен | R14: =IFERROR(INDEX(Товары_очищенные!$Q$3:$Q$503,MATCH(M14,Товары_очищенные!$L$3:$L$503,0)),"нет в каталоге") -> 137000 | S14: =IFERROR(INDEX(Товары_очищенные!$N$3:$N$503,MATCH(M14,Товары_очищенные!$L$3:$L$503,0)),"нет в каталоге") -> Телевизоры | T14: =IF(ISNUMBER(R14),IF(P14<=R14*1.5,"OK","Цена выше розницы"),"—") -> OK | U14: =TEXT(L14,"DD.MM.YYYY")&"|"&M14&"|"&F14 -> 20/01/2025|АРТ-045|C0012 | V14: =IF(COUNTIF($U$3:U14,U14)>1,"ДУБЛЬ","оригинал") -> оригинал
... A1002: 1000 | B1002: =RAW_Продажи!A1001 -> 05/29/2026 | C1002: =RAW_Продажи!B1001 -> №АРТ-357 | D1002: =RAW_Продажи!C1001 -> -3 | E1002: =RAW_Продажи!D1001 -> $120 | F1002: =RAW_Продажи!E1001 -> C1000 | G1002: =RAW_Продажи!F1001 -> P030 | H1002: =RAW_Продажи!G1001 -> завершен | I1002: =SUBSTITUTE(SUBSTITUTE(C1002,"№АРТ-",""),"АРТ_","") -> 357 | J1002: =IF(LEFT(TRIM(E1002),1)="$","$",IF(LEFT(TRIM(E1002),1)="€","€","₽")) -> $ | K1002: =VALUE(SUBSTITUTE(SUBSTITUTE(SUBSTITUTE(SUBSTITUTE(TRIM(E1002),"$",""),"€",""),"₽","")," ","")) -> 120 | L1002: =DATE(VALUE(MID(B1002,7,4)),VALUE(LEFT(B1002,2)),VALUE(MID(B1002,4,2))) -> 46171 | M1002: ="АРТ-"&LEFT(I1002,3) -> АРТ-357 | N1002: =VALUE(LEFT(TRIM(D1002),FIND(" ",TRIM(D1002)&" ")-1)) -> -3 | O1002: =IFERROR(VLOOKUP(J1002,Справочники!$G$6:$H$8,2,0),"RUB") -> USD | P1002: =ROUND(K1002*IFERROR(VLOOKUP(J1002,Справочники!$G$6:$I$8,3,0),1),2) -> 11400 | Q1002: =IFERROR(VLOOKUP(H1002,Справочники!$D$6:$E$14,2,0),"НЕИЗВЕСТНО") -> Завершен | R1002: =IFERROR(INDEX(Товары_очищенные!$Q$3:$Q$503,MATCH(M1002,Товары_очищенные!$L$3:$L$503,0)),"нет в каталоге") -> 88000 | S1002: =IFERROR(INDEX(Товары_очищенные!$N$3:$N$503,MATCH(M1002,Товары_очищенные!$L$3:$L$503,0)),"нет в каталоге") -> Смартфоны | T1002: =IF(ISNUMBER(R1002),IF(P1002<=R1002*1.5,"OK","Цена выше розницы"),"—") -> OK | U1002: =TEXT(L1002,"DD.MM.YYYY")&"|"&M1002&"|"&F1002 -> 29/05/2026|АРТ-357|C1000 | V1002: =IF(COUNTIF($U$3:U1002,U1002)>1,"ДУБЛЬ","оригинал") -> оригинал

Sheet Клиенты_очищенные
A1: ЭТАП 4 — Очистка клиентов (ФИО, даты, возраст, телефоны, email, города)
A2: № | B2: ID (ориг.) | C2: ФИО (ориг.) | D2: Дата_рожд (ориг.) | E2: Телефон (ориг.) | F2: Email (ориг.) | G2: Город (ориг.) | H2: Дата_рег (ориг.) | I2: Тел_цифры | J2: Email_без_проб | K2: Город_без_сокр | L2: ID | M2: ФИО_чист | N2: Флаг_ФИО | O2: Дата_рождения | P2: Дата_регистрации | Q2: Возраст | R2: Ошибка_возраста | S2: Телефон_чист | T2: Email_чист | U2: Ошибка_Email | V2: Город_чист
A3: 1 | B3: =RAW_Клиенты!A2 -> C0001 | C3: =RAW_Клиенты!B2 -> Иванов Иван Иванович | D3: =RAW_Клиенты!C2 -> 15.05.1990 | E3: =RAW_Клиенты!D2 -> 8-903-123-45-67 | F3: =RAW_Клиенты!E2 -> ivanov@mail.ru | G3: =RAW_Клиенты!F2 -> Москва | H3: =RAW_Клиенты!G2 -> 01.01.2022 | I3: =SUBSTITUTE(SUBSTITUTE(SUBSTITUTE(SUBSTITUTE(SUBSTITUTE(SUBSTITUTE(E3," ",""),"-",""),"+",""),"(",""),")",""),CHAR(160),"") -> 89031234567 | J3: =SUBSTITUTE(SUBSTITUTE(TRIM(F3)," ",""),CHAR(160),"") -> ivanov@mail.ru | K3: =TRIM(SUBSTITUTE(SUBSTITUTE(TRIM(G3),"г.",""),"г ","")) -> Москва | L3: =B3 -> C0001 | M3: =PROPER(TRIM(C3)) -> Иванов Иван Иванович | N3: =IF(ISNUMBER(FIND(".",C3)),"инициалы: проверить",IF(SUMPRODUCT(--ISNUMBER(FIND(MID("abcdefghijklmnopqrstuvwxyz",ROW(INDIRECT("1:26")),1),LOWER(C3))))>0,"латиница: транслит","OK")) -> 0 | O3: =IF(ISNUMBER(FIND("-",D3)),DATE(VALUE(LEFT(D3,4)),VALUE(MID(D3,6,2)),VALUE(MID(D3,9,2))),DATE(VALUE(MID(D3,7,4)),VALUE(MID(D3,4,2)),VALUE(LEFT(D3,2)))) -> 33008 | P3: =IF(ISNUMBER(FIND("-",H3)),DATE(VALUE(LEFT(H3,4)),VALUE(MID(H3,6,2)),VALUE(MID(H3,9,2))),DATE(VALUE(MID(H3,7,4)),VALUE(MID(H3,4,2)),VALUE(LEFT(H3,2)))) -> 44562 | Q3: =DATEDIF(O3,TODAY(),"Y") -> 36 | R3: =IF(OR(Q3<18,Q3>120),"Ошибка даты рождения","OK") -> OK | S3: =IF(LEN(I3)>=10,"+7 ("&MID(I3,LEN(I3)-9,3)&") "&MID(I3,LEN(I3)-6,3)&"-"&MID(I3,LEN(I3)-3,2)&"-"&RIGHT(I3,2),"Ошибка телефона") -> +7 (903) 123-45-67 | T3: =J3 -> ivanov@mail.ru | U3: =IF(AND(ISNUMBER(FIND("@",J3)),ISNUMBER(FIND(".",MID(J3,FIND("@",J3),100)))),"OK","Ошибка Email") -> OK | V3: =IFERROR(VLOOKUP(K3,Справочники!$K$6:$L$13,2,0),K3) -> Москва
A4: 2 | B4: =RAW_Клиенты!A3 -> C0002 | C4: =RAW_Клиенты!B3 -> Петров Петр Петрович | D4: =RAW_Клиенты!C3 -> 23.08.1985 | E4: =RAW_Клиенты!D3 -> +7 903 234-56-78 | F4: =RAW_Клиенты!E3 -> petrov@yandex | G4: =RAW_Клиенты!F3 -> Санкт-Петербург | H4: =RAW_Клиенты!G3 -> 2022-01-15 | I4: =SUBSTITUTE(SUBSTITUTE(SUBSTITUTE(SUBSTITUTE(SUBSTITUTE(SUBSTITUTE(E4," ",""),"-",""),"+",""),"(",""),")",""),CHAR(160),"") -> 79032345678 | J4: =SUBSTITUTE(SUBSTITUTE(TRIM(F4)," ",""),CHAR(160),"") -> petrov@yandex | K4: =TRIM(SUBSTITUTE(SUBSTITUTE(TRIM(G4),"г.",""),"г ","")) -> Санкт-Петербург | L4: =B4 -> C0002 | M4: =PROPER(TRIM(C4)) -> Петров Петр Петрович | N4: =IF(ISNUMBER(FIND(".",C4)),"инициалы: проверить",IF(SUMPRODUCT(--ISNUMBER(FIND(MID("abcdefghijklmnopqrstuvwxyz",ROW(INDIRECT("1:26")),1),LOWER(C4))))>0,"латиница: транслит","OK")) -> 0 | O4: =IF(ISNUMBER(FIND("-",D4)),DATE(VALUE(LEFT(D4,4)),VALUE(MID(D4,6,2)),VALUE(MID(D4,9,2))),DATE(VALUE(MID(D4,7,4)),VALUE(MID(D4,4,2)),VALUE(LEFT(D4,2)))) -> 31282 | P4: =IF(ISNUMBER(FIND("-",H4)),DATE(VALUE(LEFT(H4,4)),VALUE(MID(H4,6,2)),VALUE(MID(H4,9,2))),DATE(VALUE(MID(H4,7,4)),VALUE(MID(H4,4,2)),VALUE(LEFT(H4,2)))) -> 44576 | Q4: =DATEDIF(O4,TODAY(),"Y") -> 41 | R4: =IF(OR(Q4<18,Q4>120),"Ошибка даты рождения","OK") -> OK | S4: =IF(LEN(I4)>=10,"+7 ("&MID(I4,LEN(I4)-9,3)&") "&MID(I4,LEN(I4)-6,3)&"-"&MID(I4,LEN(I4)-3,2)&"-"&RIGHT(I4,2),"Ошибка телефона") -> +7 (903) 234-56-78 | T4: =J4 -> petrov@yandex | U4: =IF(AND(ISNUMBER(FIND("@",J4)),ISNUMBER(FIND(".",MID(J4,FIND("@",J4),100)))),"OK","Ошибка Email") -> Ошибка Email | V4: =IFERROR(VLOOKUP(K4,Справочники!$K$6:$L$13,2,0),K4) -> Санкт-Петербург
A5: 3 | B5: =RAW_Клиенты!A4 -> C0003 | C5: =RAW_Клиенты!B4 -> Сидоров Сидор Сидорович | D5: =RAW_Клиенты!C4 -> 12.03.1992 | E5: =RAW_Клиенты!D4 -> 8 903 345 67 89 | F5: =RAW_Клиенты!E4 -> sidorov@gmail.com | G5: =RAW_Клиенты!F4 -> Екатеринбург | H5: =RAW_Клиенты!G4 -> 15.01.2022 | I5: =SUBSTITUTE(SUBSTITUTE(SUBSTITUTE(SUBSTITUTE(SUBSTITUTE(SUBSTITUTE(E5," ",""),"-",""),"+",""),"(",""),")",""),CHAR(160),"") -> 89033456789 | J5: =SUBSTITUTE(SUBSTITUTE(TRIM(F5)," ",""),CHAR(160),"") -> sidorov@gmail.com | K5: =TRIM(SUBSTITUTE(SUBSTITUTE(TRIM(G5),"г.",""),"г ","")) -> Екатеринбург | L5: =B5 -> C0003 | M5: =PROPER(TRIM(C5)) -> Сидоров Сидор Сидорович | N5: =IF(ISNUMBER(FIND(".",C5)),"инициалы: проверить",IF(SUMPRODUCT(--ISNUMBER(FIND(MID("abcdefghijklmnopqrstuvwxyz",ROW(INDIRECT("1:26")),1),LOWER(C5))))>0,"латиница: транслит","OK")) -> 0 | O5: =IF(ISNUMBER(FIND("-",D5)),DATE(VALUE(LEFT(D5,4)),VALUE(MID(D5,6,2)),VALUE(MID(D5,9,2))),DATE(VALUE(MID(D5,7,4)),VALUE(MID(D5,4,2)),VALUE(LEFT(D5,2)))) -> 33675 | P5: =IF(ISNUMBER(FIND("-",H5)),DATE(VALUE(LEFT(H5,4)),VALUE(MID(H5,6,2)),VALUE(MID(H5,9,2))),DATE(VALUE(MID(H5,7,4)),VALUE(MID(H5,4,2)),VALUE(LEFT(H5,2)))) -> 44576 | Q5: =DATEDIF(O5,TODAY(),"Y") -> 34 | R5: =IF(OR(Q5<18,Q5>120),"Ошибка даты рождения","OK") -> OK | S5: =IF(LEN(I5)>=10,"+7 ("&MID(I5,LEN(I5)-9,3)&") "&MID(I5,LEN(I5)-6,3)&"-"&MID(I5,LEN(I5)-3,2)&"-"&RIGHT(I5,2),"Ошибка телефона") -> +7 (903) 345-67-89 | T5: =J5 -> sidorov@gmail.com | U5: =IF(AND(ISNUMBER(FIND("@",J5)),ISNUMBER(FIND(".",MID(J5,FIND("@",J5),100)))),"OK","Ошибка Email") -> OK | V5: =IFERROR(VLOOKUP(K5,Справочники!$K$6:$L$13,2,0),K5) -> Екатеринбург
A6: 4 | B6: =RAW_Клиенты!A5 -> C0004 | C6: =RAW_Клиенты!B5 -> Кузнецова Анна Сергеевна | D6: =RAW_Клиенты!C5 -> 07.11.1978 | E6: =RAW_Клиенты!D5 -> +79034567890 | F6: =RAW_Клиенты!E5 -> kuznetsova@mail | G6: =RAW_Клиенты!F5 -> Новосибирск | H6: =RAW_Клиенты!G5 -> 01.02.2022 | I6: =SUBSTITUTE(SUBSTITUTE(SUBSTITUTE(SUBSTITUTE(SUBSTITUTE(SUBSTITUTE(E6," ",""),"-",""),"+",""),"(",""),")",""),CHAR(160),"") -> 79034567890 | J6: =SUBSTITUTE(SUBSTITUTE(TRIM(F6)," ",""),CHAR(160),"") -> kuznetsova@mail | K6: =TRIM(SUBSTITUTE(SUBSTITUTE(TRIM(G6),"г.",""),"г ","")) -> Новосибирск | L6: =B6 -> C0004 | M6: =PROPER(TRIM(C6)) -> Кузнецова Анна Сергеевна | N6: =IF(ISNUMBER(FIND(".",C6)),"инициалы: проверить",IF(SUMPRODUCT(--ISNUMBER(FIND(MID("abcdefghijklmnopqrstuvwxyz",ROW(INDIRECT("1:26")),1),LOWER(C6))))>0,"латиница: транслит","OK")) -> 0 | O6: =IF(ISNUMBER(FIND("-",D6)),DATE(VALUE(LEFT(D6,4)),VALUE(MID(D6,6,2)),VALUE(MID(D6,9,2))),DATE(VALUE(MID(D6,7,4)),VALUE(MID(D6,4,2)),VALUE(LEFT(D6,2)))) -> 28801 | P6: =IF(ISNUMBER(FIND("-",H6)),DATE(VALUE(LEFT(H6,4)),VALUE(MID(H6,6,2)),VALUE(MID(H6,9,2))),DATE(VALUE(MID(H6,7,4)),VALUE(MID(H6,4,2)),VALUE(LEFT(H6,2)))) -> 44593 | Q6: =DATEDIF(O6,TODAY(),"Y") -> 47 | R6: =IF(OR(Q6<18,Q6>120),"Ошибка даты рождения","OK") -> OK | S6: =IF(LEN(I6)>=10,"+7 ("&MID(I6,LEN(I6)-9,3)&") "&MID(I6,LEN(I6)-6,3)&"-"&MID(I6,LEN(I6)-3,2)&"-"&RIGHT(I6,2),"Ошибка телефона") -> +7 (903) 456-78-90 | T6: =J6 -> kuznetsova@mail | U6: =IF(AND(ISNUMBER(FIND("@",J6)),ISNUMBER(FIND(".",MID(J6,FIND("@",J6),100)))),"OK","Ошибка Email") -> Ошибка Email | V6: =IFERROR(VLOOKUP(K6,Справочники!$K$6:$L$13,2,0),K6) -> Новосибирск
A7: 5 | B7: =RAW_Клиенты!A6 -> C0005 | C7: =RAW_Клиенты!B6 -> Смирнов Алексей Владимирович | D7: =RAW_Клиенты!C6 -> 30.06.1995 | E7: =RAW_Клиенты!D6 -> 8-903-456-78-90 | F7: =RAW_Клиенты!E6 -> smirnov@yandex | G7: =RAW_Клиенты!F6 -> Казань | H7: =RAW_Клиенты!G6 -> 2022-02-10 | I7: =SUBSTITUTE(SUBSTITUTE(SUBSTITUTE(SUBSTITUTE(SUBSTITUTE(SUBSTITUTE(E7," ",""),"-",""),"+",""),"(",""),")",""),CHAR(160),"") -> 89034567890 | J7: =SUBSTITUTE(SUBSTITUTE(TRIM(F7)," ",""),CHAR(160),"") -> smirnov@yandex | K7: =TRIM(SUBSTITUTE(SUBSTITUTE(TRIM(G7),"г.",""),"г ","")) -> Казань | L7: =B7 -> C0005 | M7: =PROPER(TRIM(C7)) -> Смирнов Алексей Владимирович | N7: =IF(ISNUMBER(FIND(".",C7)),"инициалы: проверить",IF(SUMPRODUCT(--ISNUMBER(FIND(MID("abcdefghijklmnopqrstuvwxyz",ROW(INDIRECT("1:26")),1),LOWER(C7))))>0,"латиница: транслит","OK")) -> 0 | O7: =IF(ISNUMBER(FIND("-",D7)),DATE(VALUE(LEFT(D7,4)),VALUE(MID(D7,6,2)),VALUE(MID(D7,9,2))),DATE(VALUE(MID(D7,7,4)),VALUE(MID(D7,4,2)),VALUE(LEFT(D7,2)))) -> 34880 | P7: =IF(ISNUMBER(FIND("-",H7)),DATE(VALUE(LEFT(H7,4)),VALUE(MID(H7,6,2)),VALUE(MID(H7,9,2))),DATE(VALUE(MID(H7,7,4)),VALUE(MID(H7,4,2)),VALUE(LEFT(H7,2)))) -> 44602 | Q7: =DATEDIF(O7,TODAY(),"Y") -> 31 | R7: =IF(OR(Q7<18,Q7>120),"Ошибка даты рождения","OK") -> OK | S7: =IF(LEN(I7)>=10,"+7 ("&MID(I7,LEN(I7)-9,3)&") "&MID(I7,LEN(I7)-6,3)&"-"&MID(I7,LEN(I7)-3,2)&"-"&RIGHT(I7,2),"Ошибка телефона") -> +7 (903) 456-78-90 | T7: =J7 -> smirnov@yandex | U7: =IF(AND(ISNUMBER(FIND("@",J7)),ISNUMBER(FIND(".",MID(J7,FIND("@",J7),100)))),"OK","Ошибка Email") -> Ошибка Email | V7: =IFERROR(VLOOKUP(K7,Справочники!$K$6:$L$13,2,0),K7) -> Казань
A8: 6 | B8: =RAW_Клиенты!A7 -> C0006 | C8: =RAW_Клиенты!B7 -> Попова Елена Дмитриевна | D8: =RAW_Клиенты!C7 -> 14.09.1982 | E8: =RAW_Клиенты!D7 -> 8 903 567 89 01 | F8: =RAW_Клиенты!E7 -> popova@gmail | G8: =RAW_Клиенты!F7 -> Нижний Новгород | H8: =RAW_Клиенты!G7 -> 10.02.2022 | I8: =SUBSTITUTE(SUBSTITUTE(SUBSTITUTE(SUBSTITUTE(SUBSTITUTE(SUBSTITUTE(E8," ",""),"-",""),"+",""),"(",""),")",""),CHAR(160),"") -> 89035678901 | J8: =SUBSTITUTE(SUBSTITUTE(TRIM(F8)," ",""),CHAR(160),"") -> popova@gmail | K8: =TRIM(SUBSTITUTE(SUBSTITUTE(TRIM(G8),"г.",""),"г ","")) -> Нижний Новгород | L8: =B8 -> C0006 | M8: =PROPER(TRIM(C8)) -> Попова Елена Дмитриевна | N8: =IF(ISNUMBER(FIND(".",C8)),"инициалы: проверить",IF(SUMPRODUCT(--ISNUMBER(FIND(MID("abcdefghijklmnopqrstuvwxyz",ROW(INDIRECT("1:26")),1),LOWER(C8))))>0,"латиница: транслит","OK")) -> 0 | O8: =IF(ISNUMBER(FIND("-",D8)),DATE(VALUE(LEFT(D8,4)),VALUE(MID(D8,6,2)),VALUE(MID(D8,9,2))),DATE(VALUE(MID(D8,7,4)),VALUE(MID(D8,4,2)),VALUE(LEFT(D8,2)))) -> 30208 | P8: =IF(ISNUMBER(FIND("-",H8)),DATE(VALUE(LEFT(H8,4)),VALUE(MID(H8,6,2)),VALUE(MID(H8,9,2))),DATE(VALUE(MID(H8,7,4)),VALUE(MID(H8,4,2)),VALUE(LEFT(H8,2)))) -> 44602 | Q8: =DATEDIF(O8,TODAY(),"Y") -> 44 | R8: =IF(OR(Q8<18,Q8>120),"Ошибка даты рождения","OK") -> OK | S8: =IF(LEN(I8)>=10,"+7 ("&MID(I8,LEN(I8)-9,3)&") "&MID(I8,LEN(I8)-6,3)&"-"&MID(I8,LEN(I8)-3,2)&"-"&RIGHT(I8,2),"Ошибка телефона") -> +7 (903) 567-89-01 | T8: =J8 -> popova@gmail | U8: =IF(AND(ISNUMBER(FIND("@",J8)),ISNUMBER(FIND(".",MID(J8,FIND("@",J8),100)))),"OK","Ошибка Email") -> Ошибка Email | V8: =IFERROR(VLOOKUP(K8,Справочники!$K$6:$L$13,2,0),K8) -> Нижний Новгород
A9: 7 | B9: =RAW_Клиенты!A8 -> C0007 | C9: =RAW_Клиенты!B8 -> Васильев Андрей Николаевич | D9: =RAW_Клиенты!C8 -> 25.12.1970 | E9: =RAW_Клиенты!D8 -> +79035678901 | F9: =RAW_Клиенты!E8 -> vasiliev@mail | G9: =RAW_Клиенты!F8 -> Челябинск | H9: =RAW_Клиенты!G8 -> 01.03.2022 | I9: =SUBSTITUTE(SUBSTITUTE(SUBSTITUTE(SUBSTITUTE(SUBSTITUTE(SUBSTITUTE(E9," ",""),"-",""),"+",""),"(",""),")",""),CHAR(160),"") -> 79035678901 | J9: =SUBSTITUTE(SUBSTITUTE(TRIM(F9)," ",""),CHAR(160),"") -> vasiliev@mail | K9: =TRIM(SUBSTITUTE(SUBSTITUTE(TRIM(G9),"г.",""),"г ","")) -> Челябинск | L9: =B9 -> C0007 | M9: =PROPER(TRIM(C9)) -> Васильев Андрей Николаевич | N9: =IF(ISNUMBER(FIND(".",C9)),"инициалы: проверить",IF(SUMPRODUCT(--ISNUMBER(FIND(MID("abcdefghijklmnopqrstuvwxyz",ROW(INDIRECT("1:26")),1),LOWER(C9))))>0,"латиница: транслит","OK")) -> 0 | O9: =IF(ISNUMBER(FIND("-",D9)),DATE(VALUE(LEFT(D9,4)),VALUE(MID(D9,6,2)),VALUE(MID(D9,9,2))),DATE(VALUE(MID(D9,7,4)),VALUE(MID(D9,4,2)),VALUE(LEFT(D9,2)))) -> 25927 | P9: =IF(ISNUMBER(FIND("-",H9)),DATE(VALUE(LEFT(H9,4)),VALUE(MID(H9,6,2)),VALUE(MID(H9,9,2))),DATE(VALUE(MID(H9,7,4)),VALUE(MID(H9,4,2)),VALUE(LEFT(H9,2)))) -> 44621 | Q9: =DATEDIF(O9,TODAY(),"Y") -> 55 | R9: =IF(OR(Q9<18,Q9>120),"Ошибка даты рождения","OK") -> OK | S9: =IF(LEN(I9)>=10,"+7 ("&MID(I9,LEN(I9)-9,3)&") "&MID(I9,LEN(I9)-6,3)&"-"&MID(I9,LEN(I9)-3,2)&"-"&RIGHT(I9,2),"Ошибка телефона") -> +7 (903) 567-89-01 | T9: =J9 -> vasiliev@mail | U9: =IF(AND(ISNUMBER(FIND("@",J9)),ISNUMBER(FIND(".",MID(J9,FIND("@",J9),100)))),"OK","Ошибка Email") -> Ошибка Email | V9: =IFERROR(VLOOKUP(K9,Справочники!$K$6:$L$13,2,0),K9) -> Челябинск
A10: 8 | B10: =RAW_Клиенты!A9 -> C0008 | C10: =RAW_Клиенты!B9 -> Зайцева Ольга Игоревна | D10: =RAW_Клиенты!C9 -> 19.04.1988 | E10: =RAW_Клиенты!D9 -> 8-903-678-90-12 | F10: =RAW_Клиенты!E9 -> zaitceva@yandex | G10: =RAW_Клиенты!F9 -> Самара | H10: =RAW_Клиенты!G9 -> 2022-03-15 | I10: =SUBSTITUTE(SUBSTITUTE(SUBSTITUTE(SUBSTITUTE(SUBSTITUTE(SUBSTITUTE(E10," ",""),"-",""),"+",""),"(",""),")",""),CHAR(160),"") -> 89036789012 | J10: =SUBSTITUTE(SUBSTITUTE(TRIM(F10)," ",""),CHAR(160),"") -> zaitceva@yandex | K10: =TRIM(SUBSTITUTE(SUBSTITUTE(TRIM(G10),"г.",""),"г ","")) -> Самара | L10: =B10 -> C0008 | M10: =PROPER(TRIM(C10)) -> Зайцева Ольга Игоревна | N10: =IF(ISNUMBER(FIND(".",C10)),"инициалы: проверить",IF(SUMPRODUCT(--ISNUMBER(FIND(MID("abcdefghijklmnopqrstuvwxyz",ROW(INDIRECT("1:26")),1),LOWER(C10))))>0,"латиница: транслит","OK")) -> 0 | O10: =IF(ISNUMBER(FIND("-",D10)),DATE(VALUE(LEFT(D10,4)),VALUE(MID(D10,6,2)),VALUE(MID(D10,9,2))),DATE(VALUE(MID(D10,7,4)),VALUE(MID(D10,4,2)),VALUE(LEFT(D10,2)))) -> 32252 | P10: =IF(ISNUMBER(FIND("-",H10)),DATE(VALUE(LEFT(H10,4)),VALUE(MID(H10,6,2)),VALUE(MID(H10,9,2))),DATE(VALUE(MID(H10,7,4)),VALUE(MID(H10,4,2)),VALUE(LEFT(H10,2)))) -> 44635 | Q10: =DATEDIF(O10,TODAY(),"Y") -> 38 | R10: =IF(OR(Q10<18,Q10>120),"Ошибка даты рождения","OK") -> OK | S10: =IF(LEN(I10)>=10,"+7 ("&MID(I10,LEN(I10)-9,3)&") "&MID(I10,LEN(I10)-6,3)&"-"&MID(I10,LEN(I10)-3,2)&"-"&RIGHT(I10,2),"Ошибка телефона") -> +7 (903) 678-90-12 | T10: =J10 -> zaitceva@yandex | U10: =IF(AND(ISNUMBER(FIND("@",J10)),ISNUMBER(FIND(".",MID(J10,FIND("@",J10),100)))),"OK","Ошибка Email") -> Ошибка Email | V10: =IFERROR(VLOOKUP(K10,Справочники!$K$6:$L$13,2,0),K10) -> Самара
A11: 9 | B11: =RAW_Клиенты!A10 -> C0009 | C11: =RAW_Клиенты!B10 -> Морозов Дмитрий Алексеевич | D11: =RAW_Клиенты!C10 -> 02.10.1993 | E11: =RAW_Клиенты!D10 -> 8 903 789 01 23 | F11: =RAW_Клиенты!E10 -> morozov@gmail | G11: =RAW_Клиенты!F10 -> Омск | H11: =RAW_Клиенты!G10 -> 15.03.2022 | I11: =SUBSTITUTE(SUBSTITUTE(SUBSTITUTE(SUBSTITUTE(SUBSTITUTE(SUBSTITUTE(E11," ",""),"-",""),"+",""),"(",""),")",""),CHAR(160),"") -> 89037890123 | J11: =SUBSTITUTE(SUBSTITUTE(TRIM(F11)," ",""),CHAR(160),"") -> morozov@gmail | K11: =TRIM(SUBSTITUTE(SUBSTITUTE(TRIM(G11),"г.",""),"г ","")) -> Омск | L11: =B11 -> C0009 | M11: =PROPER(TRIM(C11)) -> Морозов Дмитрий Алексеевич | N11: =IF(ISNUMBER(FIND(".",C11)),"инициалы: проверить",IF(SUMPRODUCT(--ISNUMBER(FIND(MID("abcdefghijklmnopqrstuvwxyz",ROW(INDIRECT("1:26")),1),LOWER(C11))))>0,"латиница: транслит","OK")) -> 0 | O11: =IF(ISNUMBER(FIND("-",D11)),DATE(VALUE(LEFT(D11,4)),VALUE(MID(D11,6,2)),VALUE(MID(D11,9,2))),DATE(VALUE(MID(D11,7,4)),VALUE(MID(D11,4,2)),VALUE(LEFT(D11,2)))) -> 34244 | P11: =IF(ISNUMBER(FIND("-",H11)),DATE(VALUE(LEFT(H11,4)),VALUE(MID(H11,6,2)),VALUE(MID(H11,9,2))),DATE(VALUE(MID(H11,7,4)),VALUE(MID(H11,4,2)),VALUE(LEFT(H11,2)))) -> 44635 | Q11: =DATEDIF(O11,TODAY(),"Y") -> 32 | R11: =IF(OR(Q11<18,Q11>120),"Ошибка даты рождения","OK") -> OK | S11: =IF(LEN(I11)>=10,"+7 ("&MID(I11,LEN(I11)-9,3)&") "&MID(I11,LEN(I11)-6,3)&"-"&MID(I11,LEN(I11)-3,2)&"-"&RIGHT(I11,2),"Ошибка телефона") -> +7 (903) 789-01-23 | T11: =J11 -> morozov@gmail | U11: =IF(AND(ISNUMBER(FIND("@",J11)),ISNUMBER(FIND(".",MID(J11,FIND("@",J11),100)))),"OK","Ошибка Email") -> Ошибка Email | V11: =IFERROR(VLOOKUP(K11,Справочники!$K$6:$L$13,2,0),K11) -> Омск
A12: 10 | B12: =RAW_Клиенты!A11 -> C0010 | C12: =RAW_Клиенты!B11 -> Соколова Екатерина Павловна | D12: =RAW_Клиенты!C11 -> 16.01.1976 | E12: =RAW_Клиенты!D11 -> +79038901234 | F12: =RAW_Клиенты!E11 -> sokolova@mail | G12: =RAW_Клиенты!F11 -> Ростов-на-Дону | H12: =RAW_Клиенты!G11 -> 01.04.2022 | I12: =SUBSTITUTE(SUBSTITUTE(SUBSTITUTE(SUBSTITUTE(SUBSTITUTE(SUBSTITUTE(E12," ",""),"-",""),"+",""),"(",""),")",""),CHAR(160),"") -> 79038901234 | J12: =SUBSTITUTE(SUBSTITUTE(TRIM(F12)," ",""),CHAR(160),"") -> sokolova@mail | K12: =TRIM(SUBSTITUTE(SUBSTITUTE(TRIM(G12),"г.",""),"г ","")) -> Ростов-на-Дону | L12: =B12 -> C0010 | M12: =PROPER(TRIM(C12)) -> Соколова Екатерина Павловна | N12: =IF(ISNUMBER(FIND(".",C12)),"инициалы: проверить",IF(SUMPRODUCT(--ISNUMBER(FIND(MID("abcdefghijklmnopqrstuvwxyz",ROW(INDIRECT("1:26")),1),LOWER(C12))))>0,"латиница: транслит","OK")) -> 0 | O12: =IF(ISNUMBER(FIND("-",D12)),DATE(VALUE(LEFT(D12,4)),VALUE(MID(D12,6,2)),VALUE(MID(D12,9,2))),DATE(VALUE(MID(D12,7,4)),VALUE(MID(D12,4,2)),VALUE(LEFT(D12,2)))) -> 27775 | P12: =IF(ISNUMBER(FIND("-",H12)),DATE(VALUE(LEFT(H12,4)),VALUE(MID(H12,6,2)),VALUE(MID(H12,9,2))),DATE(VALUE(MID(H12,7,4)),VALUE(MID(H12,4,2)),VALUE(LEFT(H12,2)))) -> 44652 | Q12: =DATEDIF(O12,TODAY(),"Y") -> 50 | R12: =IF(OR(Q12<18,Q12>120),"Ошибка даты рождения","OK") -> OK | S12: =IF(LEN(I12)>=10,"+7 ("&MID(I12,LEN(I12)-9,3)&") "&MID(I12,LEN(I12)-6,3)&"-"&MID(I12,LEN(I12)-3,2)&"-"&RIGHT(I12,2),"Ошибка телефона") -> +7 (903) 890-12-34 | T12: =J12 -> sokolova@mail | U12: =IF(AND(ISNUMBER(FIND("@",J12)),ISNUMBER(FIND(".",MID(J12,FIND("@",J12),100)))),"OK","Ошибка Email") -> Ошибка Email | V12: =IFERROR(VLOOKUP(K12,Справочники!$K$6:$L$13,2,0),K12) -> Ростов-на-Дону
A13: 11 | B13: =RAW_Клиенты!A12 -> C0011 | C13: =RAW_Клиенты!B12 -> Михайлов Сергей Иванович | D13: =RAW_Клиенты!C12 -> 28.07.1984 | E13: =RAW_Клиенты!D12 -> 8-903-890-12-34 | F13: =RAW_Клиенты!E12 -> mihailov@yandex | G13: =RAW_Клиенты!F12 -> Уфа | H13: =RAW_Клиенты!G12 -> 2022-04-10 | I13: =SUBSTITUTE(SUBSTITUTE(SUBSTITUTE(SUBSTITUTE(SUBSTITUTE(SUBSTITUTE(E13," ",""),"-",""),"+",""),"(",""),")",""),CHAR(160),"") -> 89038901234 | J13: =SUBSTITUTE(SUBSTITUTE(TRIM(F13)," ",""),CHAR(160),"") -> mihailov@yandex | K13: =TRIM(SUBSTITUTE(SUBSTITUTE(TRIM(G13),"г.",""),"г ","")) -> Уфа | L13: =B13 -> C0011 | M13: =PROPER(TRIM(C13)) -> Михайлов Сергей Иванович | N13: =IF(ISNUMBER(FIND(".",C13)),"инициалы: проверить",IF(SUMPRODUCT(--ISNUMBER(FIND(MID("abcdefghijklmnopqrstuvwxyz",ROW(INDIRECT("1:26")),1),LOWER(C13))))>0,"латиница: транслит","OK")) -> 0 | O13: =IF(ISNUMBER(FIND("-",D13)),DATE(VALUE(LEFT(D13,4)),VALUE(MID(D13,6,2)),VALUE(MID(D13,9,2))),DATE(VALUE(MID(D13,7,4)),VALUE(MID(D13,4,2)),VALUE(LEFT(D13,2)))) -> 30891 | P13: =IF(ISNUMBER(FIND("-",H13)),DATE(VALUE(LEFT(H13,4)),VALUE(MID(H13,6,2)),VALUE(MID(H13,9,2))),DATE(VALUE(MID(H13,7,4)),VALUE(MID(H13,4,2)),VALUE(LEFT(H13,2)))) -> 44661 | Q13: =DATEDIF(O13,TODAY(),"Y") -> 42 | R13: =IF(OR(Q13<18,Q13>120),"Ошибка даты рождения","OK") -> OK | S13: =IF(LEN(I13)>=10,"+7 ("&MID(I13,LEN(I13)-9,3)&") "&MID(I13,LEN(I13)-6,3)&"-"&MID(I13,LEN(I13)-3,2)&"-"&RIGHT(I13,2),"Ошибка телефона") -> +7 (903) 890-12-34 | T13: =J13 -> mihailov@yandex | U13: =IF(AND(ISNUMBER(FIND("@",J13)),ISNUMBER(FIND(".",MID(J13,FIND("@",J13),100)))),"OK","Ошибка Email") -> Ошибка Email | V13: =IFERROR(VLOOKUP(K13,Справочники!$K$6:$L$13,2,0),K13) -> Уфа
A14: 12 | B14: =RAW_Клиенты!A13 -> C0012 | C14: =RAW_Клиенты!B13 -> Федорова Татьяна Владимировна | D14: =RAW_Клиенты!C13 -> 11.03.1991 | E14: =RAW_Клиенты!D13 -> 8 903 901 23 45 | F14: =RAW_Клиенты!E13 -> fedorova@gmail | G14: =RAW_Клиенты!F13 -> Красноярск | H14: =RAW_Клиенты!G13 -> 10.04.2022 | I14: =SUBSTITUTE(SUBSTITUTE(SUBSTITUTE(SUBSTITUTE(SUBSTITUTE(SUBSTITUTE(E14," ",""),"-",""),"+",""),"(",""),")",""),CHAR(160),"") -> 89039012345 | J14: =SUBSTITUTE(SUBSTITUTE(TRIM(F14)," ",""),CHAR(160),"") -> fedorova@gmail | K14: =TRIM(SUBSTITUTE(SUBSTITUTE(TRIM(G14),"г.",""),"г ","")) -> Красноярск | L14: =B14 -> C0012 | M14: =PROPER(TRIM(C14)) -> Федорова Татьяна Владимировна | N14: =IF(ISNUMBER(FIND(".",C14)),"инициалы: проверить",IF(SUMPRODUCT(--ISNUMBER(FIND(MID("abcdefghijklmnopqrstuvwxyz",ROW(INDIRECT("1:26")),1),LOWER(C14))))>0,"латиница: транслит","OK")) -> 0 | O14: =IF(ISNUMBER(FIND("-",D14)),DATE(VALUE(LEFT(D14,4)),VALUE(MID(D14,6,2)),VALUE(MID(D14,9,2))),DATE(VALUE(MID(D14,7,4)),VALUE(MID(D14,4,2)),VALUE(LEFT(D14,2)))) -> 33308 | P14: =IF(ISNUMBER(FIND("-",H14)),DATE(VALUE(LEFT(H14,4)),VALUE(MID(H14,6,2)),VALUE(MID(H14,9,2))),DATE(VALUE(MID(H14,7,4)),VALUE(MID(H14,4,2)),VALUE(LEFT(H14,2)))) -> 44661 | Q14: =DATEDIF(O14,TODAY(),"Y") -> 35 | R14: =IF(OR(Q14<18,Q14>120),"Ошибка даты рождения","OK") -> OK | S14: =IF(LEN(I14)>=10,"+7 ("&MID(I14,LEN(I14)-9,3)&") "&MID(I14,LEN(I14)-6,3)&"-"&MID(I14,LEN(I14)-3,2)&"-"&RIGHT(I14,2),"Ошибка телефона") -> +7 (903) 901-23-45 | T14: =J14 -> fedorova@gmail | U14: =IF(AND(ISNUMBER(FIND("@",J14)),ISNUMBER(FIND(".",MID(J14,FIND("@",J14),100)))),"OK","Ошибка Email") -> Ошибка Email | V14: =IFERROR(VLOOKUP(K14,Справочники!$K$6:$L$13,2,0),K14) -> Красноярск
... A1002: 1000 | B1002: =RAW_Клиенты!A1001 -> C1000 | C1002: =RAW_Клиенты!B1001 -> Толстых Андрей Олегович | D1002: =RAW_Клиенты!C1001 -> 10.08.1984 | E1002: =RAW_Клиенты!D1001 -> +79039012345 | F1002: =RAW_Клиенты!E1001 -> tolstyh@mail | G1002: =RAW_Клиенты!F1001 -> Якутск | H1002: =RAW_Клиенты!G1001 -> 01.10.2049 | I1002: =SUBSTITUTE(SUBSTITUTE(SUBSTITUTE(SUBSTITUTE(SUBSTITUTE(SUBSTITUTE(E1002," ",""),"-",""),"+",""),"(",""),")",""),CHAR(160),"") -> 79039012345 | J1002: =SUBSTITUTE(SUBSTITUTE(TRIM(F1002)," ",""),CHAR(160),"") -> tolstyh@mail | K1002: =TRIM(SUBSTITUTE(SUBSTITUTE(TRIM(G1002),"г.",""),"г ","")) -> Якутск | L1002: =B1002 -> C1000 | M1002: =PROPER(TRIM(C1002)) -> Толстых Андрей Олегович | N1002: =IF(ISNUMBER(FIND(".",C1002)),"инициалы: проверить",IF(SUMPRODUCT(--ISNUMBER(FIND(MID("abcdefghijklmnopqrstuvwxyz",ROW(INDIRECT("1:26")),1),LOWER(C1002))))>0,"латиница: транслит","OK")) -> OK | O1002: =IF(ISNUMBER(FIND("-",D1002)),DATE(VALUE(LEFT(D1002,4)),VALUE(MID(D1002,6,2)),VALUE(MID(D1002,9,2))),DATE(VALUE(MID(D1002,7,4)),VALUE(MID(D1002,4,2)),VALUE(LEFT(D1002,2)))) -> 30904 | P1002: =IF(ISNUMBER(FIND("-",H1002)),DATE(VALUE(LEFT(H1002,4)),VALUE(MID(H1002,6,2)),VALUE(MID(H1002,9,2))),DATE(VALUE(MID(H1002,7,4)),VALUE(MID(H1002,4,2)),VALUE(LEFT(H1002,2)))) -> 54697 | Q1002: =DATEDIF(O1002,TODAY(),"Y") -> 42 | R1002: =IF(OR(Q1002<18,Q1002>120),"Ошибка даты рождения","OK") -> OK | S1002: =IF(LEN(I1002)>=10,"+7 ("&MID(I1002,LEN(I1002)-9,3)&") "&MID(I1002,LEN(I1002)-6,3)&"-"&MID(I1002,LEN(I1002)-3,2)&"-"&RIGHT(I1002,2),"Ошибка телефона") -> +7 (903) 901-23-45 | T1002: =J1002 -> tolstyh@mail | U1002: =IF(AND(ISNUMBER(FIND("@",J1002)),ISNUMBER(FIND(".",MID(J1002,FIND("@",J1002),100)))),"OK","Ошибка Email") -> Ошибка Email | V1002: =IFERROR(VLOOKUP(K1002,Справочники!$K$6:$L$13,2,0),K1002) -> Якутск

Sheet Справочники
A1: СПРАВОЧНИКИ СООТВЕТСТВИЙ
A2: Используются функцией ВПР (VLOOKUP) на листах очистки для нормализации категорий, статусов, валют и городов.
A4: Категории | D4: Статусы | G4: Валюты (курс к рублю) | K4: Города (нормализация сокращений)
D5: Статус_исходный | E5: Статус_эталон | G5: Символ | H5: Валюта | I5: Курс_руб | K5: Город_исходный | L5: Город_эталон
A6: Смартфоны | B6: Смартфоны | D6: Завершен | E6: Завершен | G6: $ | H6: USD | I6: 95 | K6: МСК | L6: Москва
A7: Телефоны | B7: Смартфоны | D7: завершен | E7: Завершен | G7: € | H7: EUR | I7: 100 | K7: Мск | L7: Москва
A8: Мобильные телефоны | B8: Смартфоны | D8: completed | E8: Завершен | G8: ₽ | H8: RUB | I8: 1 | K8: СПб | L8: Санкт-Петербург
A9: Ноутбуки | B9: Ноутбуки | D9: выполнен | E9: Завершен | K9: СПБ | L9: Санкт-Петербург
A10: Лэптопы | B10: Ноутбуки | D10: Отменен | E10: Отменен | K10: Питер | L10: Санкт-Петербург
A11: Планшеты | B11: Планшеты | D11: отменен | E11: Отменен | K11: Ебург | L11: Екатеринбург
A12: Телевизоры | B12: Телевизоры | D12: canceled | E12: Отменен | K12: Екб | L12: Екатеринбург
A13: Наушники | B13: Наушники | D13: Возврат | E13: Возврат | K13: НН | L13: Нижний Новгород
A14: Мониторы | B14: Мониторы | D14: возврат | E14: Возврат
A15: Аксессуары | B15: Аксессуары | K15: Города чистятся так: снять «г.»/«г », пробелы, затем ВПР по этому справочнику для известных сокращений.
A16: Часы | B16: Часы

Sheet Итоговый_отчёт
A1: ИТОГОВЫЙ ОТЧЁТ ПО ОЧИСТКЕ ДАННЫХ «ТехноОфис»
A2: Вся статистика рассчитана формулами (СЧЁТЗ, СЧЁТЕСЛИ) по очищенным листам — при изменении данных пересчитывается автоматически.
A4: 1. Количество строк по файлам
A5: Файл | B5: Строк до очистки | C5: Строк после очистки | D5: Изменение
A6: Товары | B6: =COUNTA(RAW_Товары!A2:A502) -> 501 | C6: =COUNTA(Товары_очищенные!L3:L503) -> 501 | D6: =C6-B6 -> 0
A7: Поставщики | B7: =COUNTA(RAW_Поставщики!A2:A51) -> 50 | C7: =COUNTA(Поставщики_очищенные!M3:M52) -> 50 | D7: =C7-B7 -> 0
A8: Продажи | B8: =COUNTA(RAW_Продажи!A2:A1001) -> 1000 | C8: =COUNTA(Продажи_очищенные!M3:M1002) -> 1000 | D8: =C8-B8 -> 0
A9: Клиенты | B9: =COUNTA(RAW_Клиенты!A2:A1001) -> 1000 | C9: =COUNTA(Клиенты_очищенные!L3:L1002) -> 1000 | D9: =C9-B9 -> 0
A11: 2. Выявленные ошибки по типам
A12: Тип ошибки | B12: Файл | C12: Количество
A13: Некорректный ИНН | B13: Поставщики | C13: =COUNTIF(Поставщики_очищенные!P3:P52,"Ошибка ИНН") -> 16
A14: Некорректный Email | B14: Поставщики | C14: =COUNTIF(Поставщики_очищенные!T3:T52,"Ошибка Email") -> 46
A15: Некорректный Email | B15: Клиенты | C15: =COUNTIF(Клиенты_очищенные!U3:U1002,"Ошибка Email") -> 998
A16: Ошибка даты рождения (возраст) | B16: Клиенты | C16: =COUNTIF(Клиенты_очищенные!R3:R1002,"Ошибка даты рождения") -> 0
A17: Ошибка телефона | B17: Поставщики | C17: =COUNTIF(Поставщики_очищенные!R3:R52,"Ошибка телефона") -> 0
A18: Ошибка цены (розница<закупки) | B18: Товары | C18: =COUNTIF(Товары_очищенные!S3:S503,"*ОШИБКА*") -> 0
A19: Неизвестный статус | B19: Продажи | C19: =COUNTIF(Продажи_очищенные!Q3:Q1002,"НЕИЗВЕСТНО") -> 0
A22: 3. Дубликаты продаж
A23: Найдено дубликатов (по Дата+Артикул+Клиент) | C23: =COUNTIF(Продажи_очищенные!V3:V1002,"ДУБЛЬ") -> 0
A25: 4. Распределение статусов продаж
A26: Статус | B26: Количество
A27: Завершен | B27: =COUNTIF(Продажи_очищенные!Q3:Q1002,"Завершен") -> 539
A28: Отменен | B28: =COUNTIF(Продажи_очищенные!Q3:Q1002,"Отменен") -> 307
A29: Возврат | B29: =COUNTIF(Продажи_очищенные!Q3:Q1002,"Возврат") -> 154
A31: 5. Выручка (руб.) по категориям — завершённые продажи
A32: Категория | B32: Выручка, руб.
A33: Смартфоны | B33: =SUMIFS(Продажи_очищенные!P3:P1002,Продажи_очищенные!S3:S1002,A33,Продажи_очищенные!Q3:Q1002,"Завершен") -> 706450
A34: Ноутбуки | B34: =SUMIFS(Продажи_очищенные!P3:P1002,Продажи_очищенные!S3:S1002,A34,Продажи_очищенные!Q3:Q1002,"Завершен") -> 523750
A35: Планшеты | B35: =SUMIFS(Продажи_очищенные!P3:P1002,Продажи_очищенные!S3:S1002,A35,Продажи_очищенные!Q3:Q1002,"Завершен") -> 468000
A36: Телевизоры | B36: =SUMIFS(Продажи_очищенные!P3:P1002,Продажи_очищенные!S3:S1002,A36,Продажи_очищенные!Q3:Q1002,"Завершен") -> 674300
A37: Наушники | B37: =SUMIFS(Продажи_очищенные!P3:P1002,Продажи_очищенные!S3:S1002,A37,Продажи_очищенные!Q3:Q1002,"Завершен") -> 711025
A38: Мониторы | B38: =SUMIFS(Продажи_очищенные!P3:P1002,Продажи_очищенные!S3:S1002,A38,Продажи_очищенные!Q3:Q1002,"Завершен") -> 683475
A39: Аксессуары | B39: =SUMIFS(Продажи_очищенные!P3:P1002,Продажи_очищенные!S3:S1002,A39,Продажи_очищенные!Q3:Q1002,"Завершен") -> 609475
A40: Часы | B40: =SUMIFS(Продажи_очищенные!P3:P1002,Продажи_очищенные!S3:S1002,A40,Продажи_очищенные!Q3:Q1002,"Завершен") -> 375100

Sheet Макрос
B1: МАКРОС ПРОВЕРКИ ДАННЫХ (Р7-ОФИС, Automation API) | C1: Проверка завершена. Подсвечено ячеек: 1064
B2: Реализация усложнения кейса через макрос Р7-Офис. Макрос выполняет автоматическую проверку очищенных данных и визуальную маркировку ошибок.
B4: Назначение
B5: Макрос обходит листы «Товары_очищенные», «Поставщики_очищенные», «Продажи_очищенные», «Клиенты_очищенные» и выделяет красным цветом все ячейки, значение которых содержит «Ошибка» или «ДУБЛЬ». В ячейку A1 активного листа выводится количество найденных ошибок.
B6: Запуск: вкладка «Плагины» → «Макросы» → вставить код → выполнить.
B8: Использованные методы API
B9: Api.GetSheets, ApiWorksheet.GetName, ApiWorksheet.GetUsedRange, ApiRange.ForEach, ApiRange.GetValue, ApiRange.SetFillColor, ApiRange.SetFontColor, Api.CreateColorFromRGB.
B11: Код макроса
B12: (function () {
B13: var targets = ["Товары_очищенные", "Поставщики_очищенные",
B14: "Продажи_очищенные", "Клиенты_очищенные"];
B15: var redFill = Api.CreateColorFromRGB(255, 199, 206);
B16: var redFont = Api.CreateColorFromRGB(156, 0, 6);
... B37: })();

Sheet RAW_Товары
A1: Артикул | B1: Наименование | C1: Категория | D1: Производитель | E1: Цена_закупки | F1: Цена_розница | G1: Единица_измерения
A2: №АРТ-001/24 | B2: Смартфон Apple iPhone 15 | C2: Смартфоны | D2: Apple | E2: 45 000,50 | F2: 79 990,00 | G2: шт
A3: АРТ_002 | B3: смартфон APPLE IPHONE 15 | C3: Телефоны | D3: Apple | E3: 44 500,00 | F3: 78 500,00 | G3: штука
A4: 003/24 | B4: Смартфон Apple iPhone 15 (Черный) | C4: Мобильные телефоны | D4: APPLE | E4: 43 800,00 | F4: 77 700 | G4: штуки
A5: №АРТ-004 | B5: Ноутбук ASUS ROG Zephyrus | C5: Ноутбуки | D5: ASUS | E5: 85 000 | F5: 129 999.99 | G5: шт.
A6: АРТ_005 | B6: ноутбук ASUS ROG Zephyrus | C6: Лэптопы | D6: asus | E6: 84 500,50 | F6: 128 500,00 | G6: шт
A7: 006-24 | B7: Ноутбук ASUS ROG Zephyrus (G14) | C7: Ноутбуки | D7: ASUS | E7: 86 000 | F7: 131 000 | G7: штука
A8: №АРТ-007 | B8: Смартфон Samsung Galaxy S24 | C8: Смартфоны | D8: Samsung | E8: 39 999,99 | F8: 69 999,00 | G8: шт.
A9: АРТ_008 | B9: смартфон SAMSUNG GALAXY S24 | C9: Телефоны | D9: SAMSUNG | E9: 39 500 | F9: 68 900 | G9: штуки
A10: 009/24 | B10: Смартфон Samsung Galaxy S24 (Синий) | C10: Мобильные телефоны | D10: Samsung | E10: 40 200 | F10: 70 500 | G10: шт
A11: №АРТ-010 | B11: Планшет iPad Pro 12.9 | C11: Планшеты | D11: Apple | E11: 55 000 | F11: 89 900 | G11: шт.
A12: АРТ_011 | B12: планшет APPLE IPAD PRO 12.9 | C12: Планшеты | D12: apple | E12: 54 500 | F12: 88 500 | G12: штука
... A502: 501/24 | B502: Клавиатура Logitech POP Keys (Pink) | C502: Аксессуары | D502: LOGITECH | E502: 4 000 | F502: 6 800 | G502: шт
I504: Исходные данные «как есть». Все листы очистки ссылаются на этот лист формулами.

Sheet RAW_Поставщики
A1: ID_поставщика | B1: Название | C1: ИНН | D1: КПП | E1: Телефон | F1: Email | G1: Адрес
A2: P001 | B2: ООО ТехноСнаб | C2: 7708123456 | D2: 770801001 | E2: 8-903-123-45-67 | F2: info@tehnosnab.ru | G2: 125009 г.Москва ул.Тверская д.15
A3: P002 | B3: ЗАО ЭлектроПром | C3: 7812345678123 | D3: 781201001 | E3: +7 903 234-56-78 | F3: zakaz@electroprom | G3: 191186 г.Санкт-Петербург Невский пр.д.28
A4: P003 | B4: ООО КомплектСервис | C4: 77098765 | D4: 770901001 | E4: 8 903 345 67 89 | F4: komplekt@mail.ru | G4: 127006 г.Москва ул.Петровка д.20
A5: P004 | B5: АО ТехноИмпорт | C5: 7712345678 | D5: 771001001 | E5: +79034567890 | F5: import@techno | G5: 119019 г.Москва ул.Арбат д.12
A6: P005 | B6: ООО ТоргМастер | C6: 7801234567890 | D6: 780101001 | E6: 8-903-567-89-01 | F6: torg@master | G6: 192007 г.Санкт-Петербург пр.Обуховской Обороны д.120
A7: P006 | B7: ЗАО Техноресурс | C7: 77134567 | D7: 771101001 | E7: 8-903-678-90-12 | F7: resurs@techno.ru | G7: 119121 г.Москва ул.Плющиха д.25
A8: P007 | B8: ООО ПрогрессПлюс | C8: 7802345678 | D8: 780201001 | E8: +7 903 789-01-23 | F8: progress@mail | G8: 197022 г.Санкт-Петербург ул.Профессора Попова д.37
A9: P008 | B9: АО ЭлектронСбыт | C9: 771456789012 | D9: 771201001 | E9: 8-903-890-12-34 | F9: electron@sbyt | G9: 109316 г.Москва ул.Таганская д.54
A10: P009 | B10: ООО СмартТех | C10: 7803456789 | D10: 780301001 | E10: +79039012345 | F10: smart@tech | G10: 196084 г.Санкт-Петербург ул.Заставская д.22
A11: P010 | B11: ЗАО ТехноПром | C11: 7715678901 | D11: 771301001 | E11: 8-903-012-34-56 | F11: prom@tehno | G11: 119334 г.Москва ул.Косыгина д.17
A12: P011 | B12: ООО СервисПлюс | C12: 78045678 | D12: 780401001 | E12: 8-903-123-45-67 | F12: service@plus.ru | G12: 199178 г.Санкт-Петербург ул.Средний пр.В.О.д.78
... A51: P050 | B51: ЗАО ТехноПроект | C51: 7735678901 | D51: 773301001 | E51: 8-903-012-34-56 | F51: proekt@tehno | G51: 119435 г.Москва ул.Погодинская д.18
I53: Исходные данные «как есть». Все листы очистки ссылаются на этот лист формулами.

Sheet RAW_Продажи
A1: Дата | B1: Артикул | C1: Количество | D1: Цена_продажи | E1: ID_клиента | F1: ID_поставщика | G1: Статус
A2: 01/15/2025 | B2: №АРТ-045 | C2: 2 | D2: $100 | E2: C0001 | F2: P012 | G2: Завершен
A3: 01/15/2025 | B3: АРТ_112 | C3: 1 | D3: €85 | E3: C0002 | F3: P007 | G3: завершен
A4: 01/16/2025 | B4: 003/24 | C4: 3 шт. | D4: 7500 ₽ | E4: C0003 | F4: P023 | G4: completed
A5: 01/16/2025 | B5: №АРТ-234 | C5: -1 | D5: $110 | E5: C0004 | F5: P045 | G5: отменен
A6: 01/17/2025 | B6: АРТ_067 | C6: 2 шт | D6: €90 | E6: C0005 | F6: P008 | G6: canceled
A7: 01/17/2025 | B7: 078-24 | C7: 1 | D7: 8000 ₽ | E7: C0006 | F7: P031 | G7: возврат
A8: 01/18/2025 | B8: №АРТ-389 | C8: 3 | D8: $105 | E8: C0007 | F8: P019 | G8: Завершен
A9: 01/18/2025 | B9: АРТ_156 | C9: 2 | D9: €95 | E9: C0008 | F9: P042 | G9: completed
A10: 01/19/2025 | B10: 251/24 | C10: 1 шт. | D10: 6500 ₽ | E10: C0009 | F10: P005 | G10: завершен
A11: 01/19/2025 | B11: №АРТ-023 | C11: -2 | D11: $115 | E11: C0010 | F11: P036 | G11: Отменен
A12: 01/20/2025 | B12: АРТ_478 | C12: 3 | D12: €80 | E12: C0011 | F12: P014 | G12: возврат
... A1001: 05/29/2026 | B1001: №АРТ-357 | C1001: -3 | D1001: $120 | E1001: C1000 | F1001: P030 | G1001: завершен
I1003: Исходные данные «как есть». Все листы очистки ссылаются на этот лист формулами.

Sheet RAW_Клиенты
A1: ID_клиента | B1: ФИО | C1: Дата_рождения | D1: Телефон | E1: Email | F1: Город | G1: Дата_регистрации
A2: C0001 | B2: Иванов Иван Иванович | C2: 15.05.1990 | D2: 8-903-123-45-67 | E2: ivanov@mail.ru | F2: Москва | G2: 01.01.2022
A3: C0002 | B3: Петров Петр Петрович | C3: 23.08.1985 | D3: +7 903 234-56-78 | E3: petrov@yandex | F3: Санкт-Петербург | G3: 2022-01-15
A4: C0003 | B4: Сидоров Сидор Сидорович | C4: 12.03.1992 | D4: 8 903 345 67 89 | E4: sidorov@gmail.com | F4: Екатеринбург | G4: 15.01.2022
A5: C0004 | B5: Кузнецова Анна Сергеевна | C5: 07.11.1978 | D5: +79034567890 | E5: kuznetsova@mail | F5: Новосибирск | G5: 01.02.2022
A6: C0005 | B6: Смирнов Алексей Владимирович | C6: 30.06.1995 | D6: 8-903-456-78-90 | E6: smirnov@yandex | F6: Казань | G6: 2022-02-10
A7: C0006 | B7: Попова Елена Дмитриевна | C7: 14.09.1982 | D7: 8 903 567 89 01 | E7: popova@gmail | F7: Нижний Новгород | G7: 10.02.2022
A8: C0007 | B8: Васильев Андрей Николаевич | C8: 25.12.1970 | D8: +79035678901 | E8: vasiliev@mail | F8: Челябинск | G8: 01.03.2022
A9: C0008 | B9: Зайцева Ольга Игоревна | C9: 19.04.1988 | D9: 8-903-678-90-12 | E9: zaitceva@yandex | F9: Самара | G9: 2022-03-15
A10: C0009 | B10: Морозов Дмитрий Алексеевич | C10: 02.10.1993 | D10: 8 903 789 01 23 | E10: morozov@gmail | F10: Омск | G10: 15.03.2022
A11: C0010 | B11: Соколова Екатерина Павловна | C11: 16.01.1976 | D11: +79038901234 | E11: sokolova@mail | F11: Ростов-на-Дону | G11: 01.04.2022
A12: C0011 | B12: Михайлов Сергей Иванович | C12: 28.07.1984 | D12: 8-903-890-12-34 | E12: mihailov@yandex | F12: Уфа | G12: 2022-04-10
... A1001: C1000 | B1001: Толстых Андрей Олегович | C1001: 10.08.1984 | D1001: +79039012345 | E1001: tolstyh@mail | F1001: Якутск | G1001: 01.10.2049
I1003: Исходные данные «как есть». Все листы очистки ссылаются на этот лист формулами.
